Workbook
Name \M: #REF!
Name \P: #REF!
Name \S: #REF!
Name \U: #REF!
Name ___LO1073: #REF!
Name ___LO1077: #REF!
Name ___LO1082: #REF!
Name ___LO1084: #REF!
Name ___LO802067: #REF!
Name __LO1073: #REF!
Name __LO1077: #REF!
Name __LO1082: #REF!
Name __LO1084: #REF!
Name __LO802067: #REF!
Name __USQ3: #REF!
Name _1pa: #REF!
Name _2â____Z: #REF!,#REF!,#REF!,#REF!
Name _30_Char: #REF!
Name _Day1: #REF!
Name _Day30: #REF!
Name _FTE12: #REF!
Name _JAN10: #REF!
Name _JAN17: #REF!
Name _JAN24: #REF!
Name _LO1073: #REF!
Name _LO1077: #REF!
Name _LO1082: #REF!
Name _LO1084: #REF!
Name _LO802067: #REF!
Name _pa: #REF!
Name _ProdPercent: #REF!
Name _Productlines: #REF!
Name _sch1: #REF!
Name _sch2: #REF!
Name _Table1_In1: #REF!
Name _us59022: #REF!
Name _USQ1: #REF!
Name _USQ2: #REF!
Name _USQ3: #REF!
Name _USQ4: #REF!
Name _USQ499: #REF!
Name a: #REF!
Name aaBalSheet: #REF!,#REF!
Name aaPL: #REF!,#REF!
Name abc: #REF!
Name AccessLoad: #REF!
Name Account: #REF!
Name ACCOUNT_MAP: #REF!
Name Account_Mapx: #REF!
Name ACCOUNTEDPERIODTYPE1: #REF!
Name ACCOUNTEDPERIODTYPE2: #REF!
Name Accounts: #REF!
Name AccruedInc: #REF!
Name AccruedInterest: #REF!
Name AccruedInterest2: #REF!
Name AccruedInterest2.1: #REF!
Name AccruedWages2: #REF!
Name Acct: #REF!
Name ActualISData: #REF!
Name ajlaJLAjsoaKPOA: #REF!

Sheet Pacing - Yearly Summary
B2: PodcastOne - Pacing Summary Actuals
B3: Revised Revenue Categories
C4: Fiscal 2026 | I4: Fiscal 2025 | O4: This will not change (please create)
B5: Gross Revenue | C5: Q1 | D5: Q2 | E5: Q3 | F5: Q4 | G5: FY2026 YTD YTD | I5: Q1 | J5: Q2 | K5: Q3 | L5: Q4 | M5: FY2025 YTD YTD
B6: BNB – Embedded Direct | C6: ='Pacing - Act. vs Budget'!C7 -> 4751.7107 | D6: ='Pacing - Act. vs Budget'!D7 -> 4349.9493 | E6: ='Pacing - Act. vs Budget'!E7 -> 5414.6743 | F6: ='Pacing - Act. vs Budget'!F7 -> 4357.1672 | G6: =SUM(C6:F6) -> 18873.501 | I6: ='Pacing - Monthly Inputs (actual'!P59 -> 4183.7688 | J6: ='Pacing - Monthly Inputs (actual'!Q59 -> 4043.8303 | K6: ='Pacing - Monthly Inputs (actual'!R59 -> 4372.2885 | L6: ='Pacing - Monthly Inputs (actual'!S59 -> 4205.4572 | M6: =SUM(I6:L6) -> 16805.345
B7: BNB – DAI Direct | C7: ='Pacing - Act. vs Budget'!C8 -> 436.82173 | D7: ='Pacing - Act. vs Budget'!D8 -> 439.09065 | E7: ='Pacing - Act. vs Budget'!E8 -> 591.71399 | F7: ='Pacing - Act. vs Budget'!F8 -> 540.83219 | G7: =SUM(C7:F7) -> 2008.4586 | I7: ='Pacing - Monthly Inputs (actual'!P60 -> 633.39124 | J7: ='Pacing - Monthly Inputs (actual'!Q60 -> 663.67052 | K7: ='Pacing - Monthly Inputs (actual'!R60 -> 804.12394 | L7: ='Pacing - Monthly Inputs (actual'!S60 -> 646.25655 | M7: =SUM(I7:L7) -> 2747.4423
B8: BNB – Other (social / segments / other) | C8: ='Pacing - Act. vs Budget'!C9 -> 189.65 | D8: ='Pacing - Act. vs Budget'!D9 -> 97 | E8: ='Pacing - Act. vs Budget'!E9 -> 41 | F8: ='Pacing - Act. vs Budget'!F9 -> 159.625 | G8: =SUM(C8:F8) -> 487.275 | I8: ='Pacing - Monthly Inputs (actual'!P61 -> 0 | J8: ='Pacing - Monthly Inputs (actual'!Q61 -> 0 | K8: ='Pacing - Monthly Inputs (actual'!R61 -> 0 | L8: ='Pacing - Monthly Inputs (actual'!S61 -> 127.15 | M8: =SUM(I8:L8) -> 127.15 | O8: Create and pull data from referenced cell
B9: Programmatic Revenue | C9: ='Pacing - Act. vs Budget'!C10 -> 327.33863 | D9: ='Pacing - Act. vs Budget'!D10 -> 512.40969 | E9: ='Pacing - Act. vs Budget'!E10 -> 442.24755 | F9: ='Pacing - Act. vs Budget'!F10 -> 119.19538 | G9: =SUM(C9:F9) -> 1401.1912 | I9: ='Pacing - Monthly Inputs (actual'!P62 -> 2144.7472 | J9: ='Pacing - Monthly Inputs (actual'!Q62 -> 1501.6281 | K9: ='Pacing - Monthly Inputs (actual'!R62 -> 1513.6376 | L9: ='Pacing - Monthly Inputs (actual'!S62 -> 818.18236 | M9: =SUM(I9:L9) -> 5978.1952
B10: Art 19 - MG or billed | C10: ='Pacing - Act. vs Budget'!C11 -> 1844.7242 | D10: ='Pacing - Act. vs Budget'!D11 -> 2205.4375 | E10: ='Pacing - Act. vs Budget'!E11 -> 1841.1344 | F10: ='Pacing - Act. vs Budget'!F11 -> 139.83253 | G10: =SUM(C10:F10) -> 6031.1287 | I10: ='Pacing - Monthly Inputs (actual'!P63 -> 0 | J10: ='Pacing - Monthly Inputs (actual'!Q63 -> 0 | K10: ='Pacing - Monthly Inputs (actual'!R63 -> 0 | L10: ='Pacing - Monthly Inputs (actual'!S63 -> 728.04288 | M10: =SUM(I10:L10) -> 728.04288
B11: Podroll | C11: ='Pacing - Act. vs Budget'!C12 -> 326.84303 | D11: ='Pacing - Act. vs Budget'!D12 -> 340.19839 | E11: ='Pacing - Act. vs Budget'!E12 -> 358.03186 | F11: ='Pacing - Act. vs Budget'!F12 -> 97.0868 | G11: =SUM(C11:F11) -> 1122.1601 | I11: ='Pacing - Monthly Inputs (actual'!P64 -> 0 | J11: ='Pacing - Monthly Inputs (actual'!Q64 -> 0 | K11: ='Pacing - Monthly Inputs (actual'!R64 -> 0 | L11: ='Pacing - Monthly Inputs (actual'!S64 -> 177.58563 | M11: =SUM(I11:L11) -> 177.58563
B12: PodcastOne Pro | C12: ='Pacing - Act. vs Budget'!C13 -> 12.5 | D12: ='Pacing - Act. vs Budget'!D13 -> 57.75 | E12: ='Pacing - Act. vs Budget'!E13 -> 16.5 | F12: ='Pacing - Act. vs Budget'!F13 -> 13.75 | G12: =SUM(C12:F12) -> 100.5 | I12: ='Pacing - Monthly Inputs (actual'!P65 -> 0 | J12: ='Pacing - Monthly Inputs (actual'!Q65 -> 0 | K12: ='Pacing - Monthly Inputs (actual'!R65 -> 0 | L12: ='Pacing - Monthly Inputs (actual'!S65 -> 65.75 | M12: =SUM(I12:L12) -> 65.75
B13: Subscription Revenues | C13: ='Pacing - Act. vs Budget'!C14 -> 2.57412 | D13: ='Pacing - Act. vs Budget'!D14 -> 0.02137 | E13: ='Pacing - Act. vs Budget'!E14 -> 0 | F13: ='Pacing - Act. vs Budget'!F14 -> 0 | G13: =SUM(C13:F13) -> 2.59549 | I13: ='Pacing - Monthly Inputs (actual'!P66 -> 5.648 | J13: ='Pacing - Monthly Inputs (actual'!Q66 -> 5.31966 | K13: ='Pacing - Monthly Inputs (actual'!R66 -> 5.45318 | L13: ='Pacing - Monthly Inputs (actual'!S66 -> 4.2456 | M13: =SUM(I13:L13) -> 20.66644
B14: Trade | C14: ='Pacing - Act. vs Budget'!C15 -> 0 | D14: ='Pacing - Act. vs Budget'!D15 -> 0 | E14: ='Pacing - Act. vs Budget'!E15 -> 0 | F14: ='Pacing - Act. vs Budget'!F15 -> 0 | G14: =SUM(C14:F14) -> 0 | I14: ='Pacing - Monthly Inputs (actual'!P67 -> 0 | J14: ='Pacing - Monthly Inputs (actual'!Q67 -> 0 | K14: ='Pacing - Monthly Inputs (actual'!R67 -> 0 | L14: ='Pacing - Monthly Inputs (actual'!S67 -> 0 | M14: =SUM(I14:L14) -> 0
B15: Other Revenues | C15: ='Pacing - Act. vs Budget'!C16 -> 101.73601 | D15: ='Pacing - Act. vs Budget'!D16 -> 154.30257 | E15: ='Pacing - Act. vs Budget'!E16 -> 237.09507 | F15: ='Pacing - Act. vs Budget'!F16 -> 0 | G15: =SUM(C15:F15) -> 493.13365 | I15: ='Pacing - Monthly Inputs (actual'!P68 -> 191.11728 | J15: ='Pacing - Monthly Inputs (actual'!Q68 -> -60.9117 | K15: ='Pacing - Monthly Inputs (actual'!R68 -> 14.46935 | L15: ='Pacing - Monthly Inputs (actual'!S68 -> 270.34403 | M15: =SUM(I15:L15) -> 415.01896
B16: Total (Excl Barter) | C16: =SUM(C6:C15) -> 7993.8984 | D16: =SUM(D6:D15) -> 8156.1595 | E16: =SUM(E6:E15) -> 8942.3971 | F16: =SUM(F6:F15) -> 5427.4891 | G16: =SUM(G6:G15) -> 30519.944 | I16: =SUM(I6:I15) -> 7158.6725 | J16: =SUM(J6:J15) -> 6153.5369 | K16: =SUM(K6:K15) -> 6709.9725 | L16: =SUM(L6:L15) -> 7043.0143 | M16: =SUM(M6:M15) -> 27065.196
B18: Barter | C18: ='Pacing - Act. vs Budget'!C19 -> 7000 | D18: ='Pacing - Act. vs Budget'!D19 -> 7000 | E18: ='Pacing - Act. vs Budget'!E19 -> 6913.3605 | F18: ='Pacing - Act. vs Budget'!F19 -> 7000 | G18: =SUM(C18:F18) -> 27913.361 | I18: ='Pacing - Monthly Inputs (actual'!P71 -> 6000 | J18: ='Pacing - Monthly Inputs (actual'!Q71 -> 6000 | K18: ='Pacing - Monthly Inputs (actual'!R71 -> 6000 | L18: ='Pacing - Monthly Inputs (actual'!S71 -> 7000 | M18: =SUM(I18:L18) -> 25000
B19: Total (Inc Barter) | C19: =C16+C18 -> 14993.898 | D19: =D16+D18 -> 15156.16 | E19: =E16+E18 -> 15855.758 | F19: =F16+F18 -> 12427.489 | G19: =G16+G18 -> 58433.305 | I19: =I16+I18 -> 13158.672 | J19: =J16+J18 -> 12153.537 | K19: =K16+K18 -> 12709.972 | L19: =L16+L18 -> 14043.014 | M19: =M16+M18 -> 52065.196
B21: Prior Revenue Categories
C22: Fiscal 2024 | I22: Fiscal 2023 | O22: Fiscal 2022
B23: Gross Revenue | C23: Q1 | D23: Q2 | E23: Q3 | F23: Q4 | G23: FY2024 YTD | I23: Q1 | J23: Q2 | K23: Q3 | L23: Q4 | M23: FY2023 YTD | O23: Q1 | P23: Q2 | Q23: Q3 | R23: Q4 | S23: FY2022 YTD
B24: Podcast Ads (includes Acctg entries) | C24: ='Pacing - Monthly Inputs (actual'!P78 -> 4003 | D24: ='Pacing - Monthly Inputs (actual'!Q78 -> 4364 | E24: ='Pacing - Monthly Inputs (actual'!R78 -> 5129 | F24: ='Pacing - Monthly Inputs (actual'!S78 -> 4022 | G24: =SUM(C24:F24) -> 17518 | I24: ='Pacing - Monthly Inputs (actual'!P98 -> 5530.47 | J24: ='Pacing - Monthly Inputs (actual'!Q98 -> 5309.087 | K24: ='Pacing - Monthly Inputs (actual'!R98 -> 4910.896 | L24: ='Pacing - Monthly Inputs (actual'!S98 -> 4230.0004 | M24: =SUM(I24:L24) -> 19980.453 | O24: ='Pacing - Monthly Inputs (actual'!P117 -> 4885.904 | P24: ='Pacing - Monthly Inputs (actual'!Q117 -> 5717.6507 | Q24: ='Pacing - Monthly Inputs (actual'!R117 -> 6146.2884 | R24: ='Pacing - Monthly Inputs (actual'!S117 -> 5279.2086 | S24: =SUM(O24:R24) -> 22029.052
B25: Audiomax | C25: ='Pacing - Monthly Inputs (actual'!P79 -> 2509 | D25: ='Pacing - Monthly Inputs (actual'!Q79 -> 2554 | E25: ='Pacing - Monthly Inputs (actual'!R79 -> 2106 | F25: ='Pacing - Monthly Inputs (actual'!S79 -> 1596 | G25: =SUM(C25:F25) -> 8765 | I25: ='Pacing - Monthly Inputs (actual'!P99 -> 1819.224 | J25: ='Pacing - Monthly Inputs (actual'!Q99 -> 1116.2409 | K25: ='Pacing - Monthly Inputs (actual'!R99 -> 1335.0734 | L25: ='Pacing - Monthly Inputs (actual'!S99 -> 1366.9326 | M25: =SUM(I25:L25) -> 5637.4708 | O25: ='Pacing - Monthly Inputs (actual'!P118 -> 1057.1999 | P25: ='Pacing - Monthly Inputs (actual'!Q118 -> 1158.6714 | Q25: ='Pacing - Monthly Inputs (actual'!R118 -> 1873.852 | R25: ='Pacing - Monthly Inputs (actual'!S118 -> 1396.8568 | S25: =SUM(O25:R25) -> 5486.5801
B26: Premium | C26: ='Pacing - Monthly Inputs (actual'!P80 -> 0 | D26: ='Pacing - Monthly Inputs (actual'!Q80 -> 0 | E26: ='Pacing - Monthly Inputs (actual'!R80 -> 0 | F26: ='Pacing - Monthly Inputs (actual'!S80 -> 0 | G26: =SUM(C26:F26) -> 0 | I26: ='Pacing - Monthly Inputs (actual'!P100 -> 55 | J26: ='Pacing - Monthly Inputs (actual'!Q100 -> 53 | K26: ='Pacing - Monthly Inputs (actual'!R100 -> 45 | L26: ='Pacing - Monthly Inputs (actual'!S100 -> 41 | M26: =SUM(I26:L26) -> 194 | O26: ='Pacing - Monthly Inputs (actual'!P119 -> 16 | P26: ='Pacing - Monthly Inputs (actual'!Q119 -> 15 | Q26: ='Pacing - Monthly Inputs (actual'!R119 -> 16 | R26: ='Pacing - Monthly Inputs (actual'!S119 -> 124.9 | S26: =SUM(O26:R26) -> 171.9
B27: Motortrend | C27: ='Pacing - Monthly Inputs (actual'!P81 -> 0 | D27: ='Pacing - Monthly Inputs (actual'!Q81 -> 0 | E27: ='Pacing - Monthly Inputs (actual'!R81 -> 74 | F27: ='Pacing - Monthly Inputs (actual'!S81 -> 38 | G27: =SUM(C27:F27) -> 112 | I27: ='Pacing - Monthly Inputs (actual'!P101 -> 0 | J27: ='Pacing - Monthly Inputs (actual'!Q101 -> 200 | K27: ='Pacing - Monthly Inputs (actual'!R101 -> 0 | L27: ='Pacing - Monthly Inputs (actual'!S101 -> 0 | M27: =SUM(I27:L27) -> 200 | O27: ='Pacing - Monthly Inputs (actual'!P120 -> 0 | P27: ='Pacing - Monthly Inputs (actual'!Q120 -> 0 | Q27: ='Pacing - Monthly Inputs (actual'!R120 -> 0 | R27: ='Pacing - Monthly Inputs (actual'!S120 -> 0 | S27: =SUM(O27:R27) -> 0
B28: Live Shows | C28: ='Pacing - Monthly Inputs (actual'!P82 -> 0 | D28: ='Pacing - Monthly Inputs (actual'!Q82 -> 0 | E28: ='Pacing - Monthly Inputs (actual'!R82 -> 0 | F28: ='Pacing - Monthly Inputs (actual'!S82 -> 0 | G28: =SUM(C28:F28) -> 0 | I28: 0 | J28: 0 | K28: 0 | L28: 0 | M28: =SUM(I28:L28) -> 0 | O28: 0 | P28: 0 | Q28: 0 | R28: 0 | S28: =SUM(O28:R28) -> 0
B29: Merchandise | C29: ='Pacing - Monthly Inputs (actual'!P83 -> 0 | D29: ='Pacing - Monthly Inputs (actual'!Q83 -> 0 | E29: ='Pacing - Monthly Inputs (actual'!R83 -> 0 | F29: ='Pacing - Monthly Inputs (actual'!S83 -> 0 | G29: =SUM(C29:F29) -> 0 | I29: 0 | J29: 0 | K29: 0 | L29: 0 | M29: =SUM(I29:L29) -> 0 | O29: 0 | P29: 0 | Q29: 0 | R29: 0 | S29: =SUM(O29:R29) -> 0
B30: SCA | C30: ='Pacing - Monthly Inputs (actual'!P84 -> 0 | D30: ='Pacing - Monthly Inputs (actual'!Q84 -> 0 | E30: ='Pacing - Monthly Inputs (actual'!R84 -> 0 | F30: ='Pacing - Monthly Inputs (actual'!S84 -> 0 | G30: =SUM(C30:F30) -> 0 | I30: 0 | J30: 0 | K30: 0 | L30: 0 | M30: =SUM(I30:L30) -> 0 | O30: ='Pacing - Monthly Inputs (actual'!P123 -> 58 | P30: ='Pacing - Monthly Inputs (actual'!Q123 -> 58 | Q30: ='Pacing - Monthly Inputs (actual'!R123 -> 57 | R30: ='Pacing - Monthly Inputs (actual'!S123 -> 0 | S30: =SUM(O30:R30) -> 173
B31: LXL Shared Deals | C31: ='Pacing - Monthly Inputs (actual'!P85 -> 0 | D31: ='Pacing - Monthly Inputs (actual'!Q85 -> 0 | E31: ='Pacing - Monthly Inputs (actual'!R85 -> 0 | F31: ='Pacing - Monthly Inputs (actual'!S85 -> 0 | G31: =SUM(C31:F31) -> 0 | I31: 0 | J31: 0 | K31: ='Pacing - Monthly Inputs (actual'!R105 -> 298 | L31: 0 | M31: =SUM(I31:L31) -> 298 | O31: 0 | P31: 0 | Q31: 0 | R31: 0 | S31: =SUM(O31:R31) -> 0
B32: Paywall | C32: 0 | D32: 0 | E32: 0 | F32: 0 | G32: =SUM(C32:F32) -> 0 | I32: 0 | J32: 0 | K32: 0 | L32: 0 | M32: =SUM(I32:L32) -> 0 | O32: 0 | P32: 0 | Q32: 0 | R32: 0 | S32: =SUM(O32:R32) -> 0
B33: Total (Excl Barter) | C33: =SUM(C24:C32) -> 6512 | D33: =SUM(D24:D32) -> 6918 | E33: =SUM(E24:E32) -> 7309 | F33: =SUM(F24:F32) -> 5656 | G33: =SUM(G24:G32) -> 26395 | I33: =SUM(I24:I32) -> 7404.694 | J33: =SUM(J24:J32) -> 6678.3279 | K33: =SUM(K24:K32) -> 6588.9694 | L33: =SUM(L24:L32) -> 5637.9331 | M33: =SUM(M24:M32) -> 26309.924 | O33: =SUM(O24:O32) -> 6017.1039 | P33: =SUM(P24:P32) -> 6949.322 | Q33: =SUM(Q24:Q32) -> 8093.1404 | R33: =SUM(R24:R32) -> 6800.9654 | S33: =SUM(S24:S32) -> 27860.532
B35: Barter | C35: 4090.6323 | D35: 3591.5899 | E35: 3051.5611 | F35: 6000 | G35: =SUM(C35:F35) -> 16733.783 | I35: 1311.4808 | J35: 1820.9489 | K35: 2000 | L35: 3205.2346 | M35: =SUM(I35:L35) -> 8337.6643 | O35: 1547.65 | P35: 1521 | Q35: 0 | R35: ='Pacing - Monthly Inputs (actual'!S127 -> 1249.0047 | S35: =SUM(O35:R35) -> 4317.6547
B36: Total (Inc Barter) | C36: =C33+C35 -> 10602.632 | D36: =D33+D35 -> 10509.59 | E36: =E33+E35 -> 10360.561 | F36: =F33+F35 -> 11656 | G36: =G33+G35 -> 43128.783 | I36: =I33+I35 -> 8716.1748 | J36: =J33+J35 -> 8499.2768 | K36: =K33+K35 -> 8588.9694 | L36: =L33+L35 -> 8843.1676 | M36: =M33+M35 -> 34647.589 | O36: =O33+O35 -> 7564.7539 | P36: =P33+P35 -> 8470.322 | Q36: =Q33+Q35 -> 8093.1404 | R36: =R33+R35 -> 8049.9701 | S36: =S33+S35 -> 32178.186
A45: xx

Sheet Pacing - Act. vs Budget
B2: PodcastOne - Pacing Summary
B4: Fiscal 2026 | I4: Fiscal 2026 (FY25 Figures) | P4: Fiscal 2026
B5: Pacing | I5: Budget | P5: Variance
C6: Q1 | D6: Q2 | E6: Q3 | F6: Q4 | G6: FY2025 | J6: Q1 | K6: Q2 | L6: Q3 | M6: Q4 | N6: FY2025 | Q6: Q1 | R6: Q2 | S6: Q3 | T6: Q4 | U6: FY2025
B7: BNB – Embedded Direct | C7: ='Pacing - Monthly Inputs (actual'!P6 -> 4751.7107 | D7: ='Pacing - Monthly Inputs (actual'!Q6 -> 4349.9493 | E7: ='Pacing - Monthly Inputs (actual'!R6 -> 5414.6743 | F7: ='Pacing - Monthly Inputs (actual'!S6 -> 4357.1672 | G7: =SUM(C7:F7) -> 18873.501 | I7: =B7 -> BNB – Embedded Direct | J7: 4384.8217 | K7: 4469.6592 | L7: 4750.4145 | M7: 4000 | N7: =SUM(J7:M7) -> 17604.895 | P7: =I7 -> BNB – Embedded Direct | Q7: =C7-J7 -> 366.88901 | R7: =D7-K7 -> -119.70992 | S7: =E7-L7 -> 664.25976 | T7: =F7-M7 -> 357.1672 | U7: =SUM(Q7:T7) -> 1268.606
B8: BNB – DAI Direct | C8: ='Pacing - Monthly Inputs (actual'!P7 -> 436.82173 | D8: ='Pacing - Monthly Inputs (actual'!Q7 -> 439.09065 | E8: ='Pacing - Monthly Inputs (actual'!R7 -> 591.71399 | F8: ='Pacing - Monthly Inputs (actual'!S7 -> 540.83219 | G8: =SUM(C8:F8) -> 2008.4586 | I8: =B8 -> BNB – DAI Direct | J8: 840.706 | K8: 965.34951 | L8: 1018.5763 | M8: 635 | N8: =SUM(J8:M8) -> 3459.6318 | P8: =I8 -> BNB – DAI Direct | Q8: =C8-J8 -> -403.88427 | R8: =D8-K8 -> -526.25886 | S8: =E8-L8 -> -426.86234 | T8: =F8-M8 -> -94.16781 | U8: =SUM(Q8:T8) -> -1451.1733
B9: BNB – Other (social / segments / etc) | C9: ='Pacing - Monthly Inputs (actual'!P8 -> 189.65 | D9: ='Pacing - Monthly Inputs (actual'!Q8 -> 97 | E9: ='Pacing - Monthly Inputs (actual'!R8 -> 41 | F9: ='Pacing - Monthly Inputs (actual'!S8 -> 159.625 | G9: =SUM(C9:F9) -> 487.275 | I9: BNB – Other (social / segments / etc) | J9: ='Pacing - Monthly Inputs (actual'!W8 -> 0 | K9: ='Pacing - Monthly Inputs (actual'!X8 -> 0 | L9: ='Pacing - Monthly Inputs (actual'!Y8 -> 0 | M9: 154 | N9: =SUM(J9:M9) -> 154 | P9: =I9 -> BNB – Other (social / segments / etc) | Q9: =C9-J9 -> 189.65 | R9: =D9-K9 -> 97 | S9: =E9-L9 -> 41 | T9: =F9-M9 -> 5.625 | U9: =SUM(Q9:T9) -> 333.275
B10: Programmatic Revenue | C10: ='Pacing - Monthly Inputs (actual'!P9 -> 327.33863 | D10: ='Pacing - Monthly Inputs (actual'!Q9 -> 512.40969 | E10: ='Pacing - Monthly Inputs (actual'!R9 -> 442.24755 | F10: ='Pacing - Monthly Inputs (actual'!S9 -> 119.19538 | G10: =SUM(C10:F10) -> 1401.1912 | I10: =B10 -> Programmatic Revenue | J10: =1974506.18/1000 -> 1974.5062 | K10: =2371198.29879053/1000 -> 2371.1983 | L10: =2530310.56/1000 -> 2530.3106 | M10: 1200 | N10: =SUM(J10:M10) -> 8076.015 | P10: =I10 -> Programmatic Revenue | Q10: =C10-J10 -> -1647.1675 | R10: =D10-K10 -> -1858.7886 | S10: =E10-L10 -> -2088.063 | T10: =F10-M10 -> -1080.8046 | U10: =SUM(Q10:T10) -> -6674.8238
B11: Art 19 - MG or billed | C11: ='Pacing - Monthly Inputs (actual'!P10 -> 1844.7242 | D11: ='Pacing - Monthly Inputs (actual'!Q10 -> 2205.4375 | E11: ='Pacing - Monthly Inputs (actual'!R10 -> 1841.1344 | F11: ='Pacing - Monthly Inputs (actual'!S10 -> 139.83253 | G11: =SUM(C11:F11) -> 6031.1287 | I11: =B11 -> Art 19 - MG or billed | J11: ='Pacing - Monthly Inputs (actual'!W10 -> 0 | K11: ='Pacing - Monthly Inputs (actual'!X10 -> 0 | L11: ='Pacing - Monthly Inputs (actual'!Y10 -> 0 | M11: ='Pacing - Monthly Inputs (actual'!Z10 -> 0 | N11: =SUM(J11:M11) -> 0 | P11: =I11 -> Art 19 - MG or billed | Q11: =C11-J11 -> 1844.7242 | R11: =D11-K11 -> 2205.4375 | S11: =E11-L11 -> 1841.1344 | T11: =F11-M11 -> 139.83253 | U11: =SUM(Q11:T11) -> 6031.1287
B12: Podroll | C12: ='Pacing - Monthly Inputs (actual'!P11 -> 326.84303 | D12: ='Pacing - Monthly Inputs (actual'!Q11 -> 340.19839 | E12: ='Pacing - Monthly Inputs (actual'!R11 -> 358.03186 | F12: ='Pacing - Monthly Inputs (actual'!S11 -> 97.0868 | G12: =SUM(C12:F12) -> 1122.1601 | I12: =B12 -> Podroll | J12: ='Pacing - Monthly Inputs (actual'!W11 -> 0 | K12: ='Pacing - Monthly Inputs (actual'!X11 -> 0 | L12: ='Pacing - Monthly Inputs (actual'!Y11 -> 0 | M12: 120 | N12: =SUM(J12:M12) -> 120 | P12: =I12 -> Podroll | Q12: =C12-J12 -> 326.84303 | R12: =D12-K12 -> 340.19839 | S12: =E12-L12 -> 358.03186 | T12: =F12-M12 -> -22.9132 | U12: =SUM(Q12:T12) -> 1002.1601
B13: PodcastOne Pro | C13: ='Pacing - Monthly Inputs (actual'!P12 -> 12.5 | D13: ='Pacing - Monthly Inputs (actual'!Q12 -> 57.75 | E13: ='Pacing - Monthly Inputs (actual'!R12 -> 16.5 | F13: ='Pacing - Monthly Inputs (actual'!S12 -> 13.75 | G13: =SUM(C13:F13) -> 100.5 | I13: =B13 -> PodcastOne Pro | J13: ='Pacing - Monthly Inputs (actual'!W12 -> 0 | K13: ='Pacing - Monthly Inputs (actual'!X12 -> 0 | L13: ='Pacing - Monthly Inputs (actual'!Y12 -> 0 | M13: 76.25 | N13: =SUM(J13:M13) -> 76.25 | P13: =I13 -> PodcastOne Pro | Q13: =C13-J13 -> 12.5 | R13: =D13-K13 -> 57.75 | S13: =E13-L13 -> 16.5 | T13: =F13-M13 -> -62.5 | U13: =SUM(Q13:T13) -> 24.25
B14: Subscription Revenues | C14: ='Pacing - Monthly Inputs (actual'!P13 -> 2.57412 | D14: ='Pacing - Monthly Inputs (actual'!Q13 -> 0.02137 | E14: ='Pacing - Monthly Inputs (actual'!R13 -> 0 | F14: ='Pacing - Monthly Inputs (actual'!S13 -> 0 | G14: =SUM(C14:F14) -> 2.59549 | I14: =B14 -> Subscription Revenues | J14: 5 | K14: 5 | L14: 5 | M14: 5 | N14: =SUM(J14:M14) -> 20 | P14: =I14 -> Subscription Revenues | Q14: =C14-J14 -> -2.42588 | R14: =D14-K14 -> -4.97863 | S14: =E14-L14 -> -5 | T14: =F14-M14 -> -5 | U14: =SUM(Q14:T14) -> -17.40451
B15: Trade | C15: ='Pacing - Monthly Inputs (actual'!P14 -> 0 | D15: ='Pacing - Monthly Inputs (actual'!Q14 -> 0 | E15: ='Pacing - Monthly Inputs (actual'!R14 -> 0 | F15: ='Pacing - Monthly Inputs (actual'!S14 -> 0 | G15: =SUM(C15:F15) -> 0 | I15: =B15 -> Trade | J15: ='Pacing - Monthly Inputs (actual'!W14 -> 0 | K15: ='Pacing - Monthly Inputs (actual'!X14 -> 0 | L15: ='Pacing - Monthly Inputs (actual'!Y14 -> 0 | M15: ='Pacing - Monthly Inputs (actual'!Z14 -> 0 | N15: =SUM(J15:M15) -> 0 | P15: =I15 -> Trade | Q15: =C15-J15 -> 0 | R15: =D15-K15 -> 0 | S15: =E15-L15 -> 0 | T15: =F15-M15 -> 0 | U15: =SUM(Q15:T15) -> 0
B16: Other Revenues | C16: ='Pacing - Monthly Inputs (actual'!P15 -> 101.73601 | D16: ='Pacing - Monthly Inputs (actual'!Q15 -> 154.30257 | E16: ='Pacing - Monthly Inputs (actual'!R15 -> 237.09507 | F16: ='Pacing - Monthly Inputs (actual'!S15 -> 0 | G16: =SUM(C16:F16) -> 493.13365 | I16: =B16 -> Other Revenues | J16: 38.75 | K16: 38.75 | L16: 38.75 | M16: 38.75 | N16: =SUM(J16:M16) -> 155 | P16: =I16 -> Other Revenues | Q16: =C16-J16 -> 62.98601 | R16: =D16-K16 -> 115.55257 | S16: =E16-L16 -> 198.34507 | T16: =F16-M16 -> -38.75 | U16: =SUM(Q16:T16) -> 338.13365
B17: Total (Excl Barter) | C17: =SUM(C7:C16) -> 7993.8984 | D17: =SUM(D7:D16) -> 8156.1595 | E17: =SUM(E7:E16) -> 8942.3971 | F17: =SUM(F7:F16) -> 5427.4891 | G17: =SUM(G7:G16) -> 30519.944 | I17: Total (Excl Barter) | J17: =SUM(J7:J16) -> 7243.7839 | K17: =SUM(K7:K16) -> 7849.957 | L17: =SUM(L7:L16) -> 8343.0514 | M17: =SUM(M7:M16) -> 6229 | N17: =SUM(N7:N16) -> 29665.792 | P17: Total (Excl Barter) | Q17: =SUM(Q7:Q16) -> 750.11452 | R17: =SUM(R7:R16) -> 306.20247 | S17: =SUM(S7:S16) -> 599.34576 | T17: =SUM(T7:T16) -> -801.5109 | U17: =SUM(U7:U16) -> 854.15185
B19: Barter | C19: ='Pacing - Monthly Inputs (actual'!P18 -> 7000 | D19: ='Pacing - Monthly Inputs (actual'!Q18 -> 7000 | E19: ='Pacing - Monthly Inputs (actual'!R18 -> 6913.3605 | F19: ='Pacing - Monthly Inputs (actual'!S18 -> 7000 | G19: =SUM(C19:F19) -> 27913.361 | I19: Barter | J19: 7000 | K19: 7000 | L19: 7000 | M19: 0 | N19: =SUM(J19:M19) -> 21000 | P19: Barter | Q19: =C19-J19 -> -6.6666671e-06 | R19: =D19-K19 -> 0 | S19: =E19-L19 -> -86.639483 | T19: =F19-M19 -> 7000 | U19: =SUM(Q19:T19) -> 6913.3605
B20: Total (Inc Barter) | C20: =C17+C19 -> 14993.898 | D20: =D17+D19 -> 15156.16 | E20: =E17+E19 -> 15855.758 | F20: =F17+F19 -> 12427.489 | G20: =G17+G19 -> 58433.305 | I20: Total (Inc Barter) | J20: =J17+J19 -> 14243.784 | K20: =K17+K19 -> 14849.957 | L20: =L17+L19 -> 15343.051 | M20: =M17+M19 -> 6229 | N20: =N17+N19 -> 50665.792 | P20: Total (Inc Barter) | Q20: =Q17+Q19 -> 750.11451 | R20: =R17+R19 -> 306.20247 | S20: =S17+S19 -> 512.70628 | T20: =T17+T19 -> 6198.4891 | U20: =U17+U19 -> 7767.5124
B25: Pacing | I25: Budget | P25: Variance
C26: Q1 | D26: Q2 | E26: Q3 | F26: Q4 | G26: FY2025 | J26: Q1 | K26: Q2 | L26: Q3 | M26: Q4 | N26: FY2025 | Q26: Q1 | R26: Q2 | S26: Q3 | T26: Q4 | U26: FY2025
B27: Direct & Other | C27: =SUM(C7:C9)+SUM(C12:C16) -> 5821.8356 | D27: =SUM(D7:D9)+SUM(D12:D16) -> 5438.3123 | E27: =SUM(E7:E9)+SUM(E12:E16) -> 6659.0152 | F27: =SUM(F7:F9)+SUM(F12:F16) -> 5168.4612 | G27: =SUM(G7:G9)+SUM(G12:G16) -> 23087.624 | I27: Direct & Other | J27: =SUM(J7:J9)+SUM(J12:J16) -> 5269.2777 | K27: =SUM(K7:K9)+SUM(K12:K16) -> 5478.7587 | L27: =SUM(L7:L9)+SUM(L12:L16) -> 5812.7408 | M27: =SUM(M7:M9)+SUM(M12:M16) -> 5029 | N27: =SUM(N7:N9)+SUM(N12:N16) -> 21589.777 | P27: Direct & Other | Q27: =SUM(Q7:Q9)+SUM(Q12:Q16) -> 552.5579 | R27: =SUM(R7:R9)+SUM(R12:R16) -> -40.446458 | S27: =SUM(S7:S9)+SUM(S12:S16) -> 846.27435 | T27: =SUM(T7:T9)+SUM(T12:T16) -> 139.46119 | U27: =SUM(U7:U9)+SUM(U12:U16) -> 1497.847
B28: Programmatic | C28: =SUM(C10:C11) -> 2172.0628 | D28: =SUM(D10:D11) -> 2717.8472 | E28: =SUM(E10:E11) -> 2283.382 | F28: =SUM(F10:F11) -> 259.02791 | G28: =SUM(G10:G11) -> 7432.3199 | I28: Programmatic | J28: =SUM(J10:J11) -> 1974.5062 | K28: =SUM(K10:K11) -> 2371.1983 | L28: =SUM(L10:L11) -> 2530.3106 | M28: =SUM(M10:M11) -> 1200 | N28: =SUM(N10:N11) -> 8076.015 | P28: Programmatic | Q28: =SUM(Q10:Q11) -> 197.55662 | R28: =SUM(R10:R11) -> 346.64893 | S28: =SUM(S10:S11) -> -246.92859 | T28: =SUM(T10:T11) -> -940.97209 | U28: =SUM(U10:U11) -> -643.69513
B29: Total (Excl Barter) | C29: =C27+C28 -> 7993.8984 | D29: =D27+D28 -> 8156.1595 | E29: =E27+E28 -> 8942.3971 | F29: =F27+F28 -> 5427.4891 | G29: =G27+G28 -> 30519.944 | I29: Total (Excl Barter) | J29: =J27+J28 -> 7243.7839 | K29: =K27+K28 -> 7849.957 | L29: =L27+L28 -> 8343.0514 | M29: =M27+M28 -> 6229 | N29: =N27+N28 -> 29665.792 | P29: Total (Excl Barter) | Q29: =Q27+Q28 -> 750.11452 | R29: =R27+R28 -> 306.20247 | S29: =S27+S28 -> 599.34576 | T29: =T27+T28 -> -801.5109 | U29: =U27+U28 -> 854.15185
A40: xx

Sheet Pacing - Monthly Inputs (actual
A3: FY 2026 | B3: Calendar Year: | C3: 2025 | D3: 2025 | E3: 2025 | F3: 2025 | G3: 2025 | H3: 2025 | I3: 2025 | J3: 2025 | K3: 2025 | L3: 2026 | M3: 2026 | N3: 2026 | P3: 2025 | Q3: 2025 | R3: 2025 | S3: 2026
B4: PodcastOne - Gross Revenue
C5: Apr | D5: May | E5: Jun | F5: Jul | G5: Aug | H5: Sep | I5: Oct | J5: Nov | K5: Dec | L5: Jan | M5: Feb | N5: Mar | P5: Q1 | Q5: Q2 | R5: Q3 | S5: Q4 | T5: FY 2026 YTD
B6: BNB – Embedded Direct | C6: =C28/1000 -> 1497.7577 | D6: =D28/1000 -> 1562.0134 | E6: =E28/1000 -> 1691.9396 | F6: =F28/1000 -> 1282.4772 | G6: =G28/1000 -> 1553.7131 | H6: =H28/1000 -> 1513.759 | I6: =I28/1000 -> 1709.7439 | J6: =J28/1000 -> 2104.719 | ... N6: =N28/1000 -> 1361.9121 | P6: =SUM(C6:E6) -> 4751.7107 | Q6: =SUM(F6:H6) -> 4349.9493 | R6: =SUM(I6:K6) -> 5414.6743 | S6: =SUM(L6:N6) -> 4357.1672 | T6: =SUM(P6:S6) -> 18873.501
B7: BNB – DAI Direct | C7: =C29/1000 -> 152.3014 | D7: =D29/1000 -> 145.69115 | E7: =E29/1000 -> 138.82918 | F7: =F29/1000 -> 106.07033 | G7: =G29/1000 -> 118.72003 | H7: =H29/1000 -> 214.30029 | I7: =I29/1000 -> 176.01305 | J7: =J29/1000 -> 209.4828 | ... N7: =N29/1000 -> 180.44142 | P7: =SUM(C7:E7) -> 436.82173 | Q7: =SUM(F7:H7) -> 439.09065 | R7: =SUM(I7:K7) -> 591.71399 | S7: =SUM(L7:N7) -> 540.83219 | T7: =SUM(P7:S7) -> 2008.4586
B8: BNB – Other (social / segments / other) | C8: =C30/1000 -> 63.65 | D8: =D30/1000 -> 58 | E8: =E30/1000 -> 68 | F8: =F30/1000 -> 47 | G8: =G30/1000 -> 35 | H8: =H30/1000 -> 15 | I8: =I30/1000 -> 22 | J8: =J30/1000 -> 4 | ... N8: =N30/1000 -> 0 | P8: =SUM(C8:E8) -> 189.65 | Q8: =SUM(F8:H8) -> 97 | R8: =SUM(I8:K8) -> 41 | S8: =SUM(L8:N8) -> 159.625 | T8: =SUM(P8:S8) -> 487.275
B9: Programmatic Revenue | C9: =C31/1000 -> 85.01987 | D9: =D31/1000 -> 79.65512 | E9: =E31/1000 -> 162.66364 | F9: =F31/1000 -> 198.94 | G9: =G31/1000 -> 158.42121 | H9: =H31/1000 -> 155.04848 | I9: =I31/1000 -> 117.23829 | J9: =J31/1000 -> 130.92886 | ... N9: =N31/1000 -> 0 | P9: =SUM(C9:E9) -> 327.33863 | Q9: =SUM(F9:H9) -> 512.40969 | R9: =SUM(I9:K9) -> 442.24755 | S9: =SUM(L9:N9) -> 119.19538 | T9: =SUM(P9:S9) -> 1401.1912
B10: Art 19 - MG or billed | C10: =C32/1000 -> 509.27201 | D10: =D32/1000 -> 536.66903 | E10: =E32/1000 -> 798.78313 | F10: =F32/1000 -> 656.47697 | G10: =G32/1000 -> 709.35747 | H10: =H32/1000 -> 839.6031 | I10: =I32/1000 -> 593.17786 | J10: =J32/1000 -> 727.53702 | ... N10: =N32/1000 -> 0 | P10: =SUM(C10:E10) -> 1844.7242 | Q10: =SUM(F10:H10) -> 2205.4375 | R10: =SUM(I10:K10) -> 1841.1344 | S10: =SUM(L10:N10) -> 139.83253 | T10: =SUM(P10:S10) -> 6031.1287
B11: Podroll | C11: =C33/1000 -> 68.11984 | D11: =D33/1000 -> 62.89096 | E11: =E33/1000 -> 195.83223 | F11: =F33/1000 -> 108.07525 | G11: =G33/1000 -> 115.10301 | H11: =H33/1000 -> 117.02013 | I11: =I33/1000 -> 125.97655 | J11: =J33/1000 -> 119.96869 | ... N11: =N33/1000 -> 0 | P11: =SUM(C11:E11) -> 326.84303 | Q11: =SUM(F11:H11) -> 340.19839 | R11: =SUM(I11:K11) -> 358.03186 | S11: =SUM(L11:N11) -> 97.0868 | T11: =SUM(P11:S11) -> 1122.1601
B12: PodcastOne Pro | C12: =C34/1000 -> 1.5 | D12: =D34/1000 -> 0 | E12: =E34/1000 -> 11 | F12: =F34/1000 -> 35.75 | G12: =G34/1000 -> 11 | H12: =H34/1000 -> 11 | I12: =I34/1000 -> 0 | J12: =J34/1000 -> 8.25 | ... N12: =N34/1000 -> 0 | P12: =SUM(C12:E12) -> 12.5 | Q12: =SUM(F12:H12) -> 57.75 | R12: =SUM(I12:K12) -> 16.5 | S12: =SUM(L12:N12) -> 13.75 | T12: =SUM(P12:S12) -> 100.5
B13: Subscription Revenues | C13: =C35/1000 -> 1.32247 | D13: =D35/1000 -> 1.11527 | E13: =E35/1000 -> 0.13638 | F13: =F35/1000 -> 0.02137 | G13: =G35/1000 -> 0 | H13: =H35/1000 -> 0 | I13: =I35/1000 -> 0 | J13: =J35/1000 -> 0 | ... N13: =N35/1000 -> 0 | P13: =SUM(C13:E13) -> 2.57412 | Q13: =SUM(F13:H13) -> 0.02137 | R13: =SUM(I13:K13) -> 0 | S13: =SUM(L13:N13) -> 0 | T13: =SUM(P13:S13) -> 2.59549
B14: Trade | C14: =C36/1000 -> 0 | D14: =D36/1000 -> 0 | E14: =E36/1000 -> 0 | F14: =F36/1000 -> 0 | G14: =G36/1000 -> 0 | H14: =H36/1000 -> 0 | I14: =I36/1000 -> 0 | J14: =J36/1000 -> 0 | ... N14: =N36/1000 -> 0 | P14: =SUM(C14:E14) -> 0 | Q14: =SUM(F14:H14) -> 0 | R14: =SUM(I14:K14) -> 0 | S14: =SUM(L14:N14) -> 0 | T14: =SUM(P14:S14) -> 0
B15: Other Revenues | C15: =C37/1000 -> 30.25166 | D15: =D37/1000 -> 28.95672 | E15: =E37/1000 -> 42.52763 | F15: =F37/1000 -> 48.89685 | G15: =G37/1000 -> 43.16521 | H15: =H37/1000 -> 62.24051 | I15: =I37/1000 -> 57.85595 | J15: =J37/1000 -> 44.21013 | ... N15: =N37/1000 -> 0 | P15: =SUM(C15:E15) -> 101.73601 | Q15: =SUM(F15:H15) -> 154.30257 | R15: =SUM(I15:K15) -> 237.09507 | S15: =SUM(L15:N15) -> 0 | T15: =SUM(P15:S15) -> 493.13365
B16: Total (Excl Barter) | C16: =SUM(C6:C15) -> 2409.195 | D16: =SUM(D6:D15) -> 2474.9917 | E16: =SUM(E6:E15) -> 3109.7117 | F16: =SUM(F6:F15) -> 2483.7079 | G16: =SUM(G6:G15) -> 2744.48 | H16: =SUM(H6:H15) -> 2927.9715 | I16: =SUM(I6:I15) -> 2802.0056 | J16: =SUM(J6:J15) -> 3349.0965 | ... N16: =SUM(N6:N15) -> 1542.3536 | P16: =SUM(P6:P15) -> 7993.8984 | Q16: =SUM(Q6:Q15) -> 8156.1595 | R16: =SUM(R6:R15) -> 8942.3971 | S16: =SUM(S6:S15) -> 5427.4891 | T16: =SUM(T6:T15) -> 30519.944
B18: Barter | C18: =C40/1000 -> 2333.3333 | D18: =D40/1000 -> 2333.3333 | E18: =E40/1000 -> 2333.3333 | F18: =F40/1000 -> 2333.3333 | G18: =G40/1000 -> 2333.3333 | H18: =H40/1000 -> 2333.3333 | I18: =I40/1000 -> 2333.3333 | J18: =J40/1000 -> 2333.3333 | ... N18: =N40/1000 -> 2333.3333 | P18: =SUM(C18:E18) -> 7000 | Q18: =SUM(F18:H18) -> 7000 | R18: =SUM(I18:K18) -> 6913.3605 | S18: =SUM(L18:N18) -> 7000 | T18: =SUM(P18:S18) -> 27913.361
B20: Total (Incl Barter) | C20: =C16+C18 -> 4742.5283 | D20: =D16+D18 -> 4808.325 | E20: =E16+E18 -> 5443.0451 | F20: =F16+F18 -> 4817.0413 | G20: =G16+G18 -> 5077.8134 | H20: =H16+H18 -> 5261.3049 | I20: =I16+I18 -> 5135.3389 | J20: =J16+J18 -> 5682.4299 | ... N20: =N16+N18 -> 3875.6869 | P20: =P16+P18 -> 14993.898 | Q20: =Q16+Q18 -> 15156.16 | R20: =R16+R18 -> 15855.758 | S20: =S16+S18 -> 12427.489 | T20: =T16+T18 -> 58433.305
C23: =(C24/1000)-C20 -> -9.9999999e-05
C24: 4742528.2
A25: xx | B25: Inputs to Feed to Summary Above:
B26: FY2025 | C26: Actual | D26: Actual | E26: Actual | F26: Actual | G26: Actual | H26: Actual | I26: Actual | J26: Actual | K26: Actual | L26: Forecast | M26: Forecast | N26: Forecast
C27: =C5 -> Apr | D27: =D5 -> May | E27: =E5 -> Jun | F27: =F5 -> Jul | G27: =G5 -> Aug | H27: =H5 -> Sep | I27: =I5 -> Oct | J27: =J5 -> Nov | ... N27: =N5 -> Mar
B28: =B6 -> BNB – Embedded Direct | C28: =1631027.58-63650-1500-201924.03+133804.19 -> 1497757.7 | D28: =1682904.37-58000-62890.96 -> 1562013.4 | E28: 1691939.6 | F28: =1473302.42-F30-F33-F34 -> 1282477.2 | G28: =1714816.12-G30-G33-G34 -> 1553713.1 | H28: =1656937.88-158.72-H30-H33-H34 -> 1513759 | I28: 1709743.9 | J28: 2104719 | K28: 1600211.3 | L28: ='Billed n Booked_Philip_02.02'!C96 -> 1564550.6 | M28: ='Billed n Booked_Philip_02.02'!D96 -> 1430704.4 | N28: ='Billed n Booked_Philip_02.02'!E96 -> 1361912.1
B29: =B7 -> BNB – DAI Direct | C29: 152301.4 | D29: 145691.15 | E29: 138829.18 | F29: 106070.33 | G29: 118720.03 | H29: 214300.29 | I29: 176013.05 | J29: 209482.8 | K29: 206218.14 | L29: ='Billed n Booked_Philip_02.02'!C94 -> 188584.07 | M29: ='Billed n Booked_Philip_02.02'!D94 -> 171806.7 | N29: ='Billed n Booked_Philip_02.02'!E94 -> 180441.42
B30: =B8 -> BNB – Other (social / segments / other) | C30: 63650 | D30: 58000 | E30: 68000 | F30: 47000 | G30: 35000 | H30: 15000 | I30: 22000 | J30: 4000 | K30: 15000 | L30: ='Billed n Booked_Philip_02.02'!C98 -> 35625 | M30: ='Billed n Booked_Philip_02.02'!D98 -> 124000 | N30: ='Billed n Booked_Philip_02.02'!E98 -> 0
B31: =B9 -> Programmatic Revenue | C31: 85019.87 | D31: 79655.12 | E31: =149611.91+11078.43+1973.3 -> 162663.64 | F31: 198940 | G31: 158421.21 | H31: 155048.48 | I31: 117238.29 | J31: 130928.86 | K31: 194080.4 | L31: =L45-L46+L47+L48+L49+L50 -> 91169.94 | M31: =M45-M46+M47+M48+M49+M50 -> 28025.44 | N31: =N45-N46+N47+N48+N49+N50 -> 0
B32: =B10 -> Art 19 - MG or billed | C32: 509272.01 | D32: 536669.03 | E32: 798783.13 | F32: 656476.97 | G32: 709357.47 | H32: 839603.1 | I32: 593177.86 | J32: 727537.02 | K32: 520419.54 | L32: =L52 -> 96456.837 | M32: =M52 -> 43375.69 | N32: =N52 -> 0
B33: =B11 -> Podroll | C33: =201924.03-133804.19 -> 68119.84 | D33: 62890.96 | E33: =65094.9899999999+130737.24 -> 195832.23 | F33: 108075.25 | G33: 115103.01 | H33: 117020.13 | I33: 125976.55 | J33: 119968.69 | K33: 112086.62 | L33: ='Billed n Booked_Philip_02.02'!C100 -> 97086.8 | M33: 0 | N33: 0
B34: =B12 -> PodcastOne Pro | C34: 1500 | D34: 0 | E34: 11000 | F34: 35750 | G34: 11000 | H34: 11000 | I34: 0 | J34: 8250 | K34: 8250 | L34: ='Billed n Booked_Philip_02.02'!C102 -> 13750 | M34: 0 | N34: 0
B35: =B13 -> Subscription Revenues | C35: 1322.47 | D35: 1115.27 | E35: 136.38 | F35: 21.37 | G35: 0 | H35: 0 | I35: 0 | J35: 0 | K35: 0 | L35: 0 | M35: 0 | N35: 0
B36: =B14 -> Trade | C36: 0 | D36: 0 | E36: 0 | F36: 0 | G36: 0 | H36: 0 | I36: 0 | J36: 0 | K36: 0 | L36: 0 | M36: 0 | N36: 0
B37: =B15 -> Other Revenues | C37: =30251.66 -> 30251.66 | D37: 28956.72 | E37: 42527.63 | F37: 48896.85 | G37: 43165.21 | H37: 62240.51 | I37: 57855.95 | J37: 44210.13 | K37: 135028.99 | L37: 0 | M37: 0 | N37: 0
B38: Total (Excl Barter) | C38: =SUM(C28:C37) -> 2409195 | D38: =SUM(D28:D37) -> 2474991.7 | E38: =SUM(E28:E37) -> 3109711.7 | F38: =SUM(F28:F37) -> 2483707.9 | G38: =SUM(G28:G37) -> 2744480 | H38: =SUM(H28:H37) -> 2927971.5 | I38: =SUM(I28:I37) -> 2802005.6 | J38: =SUM(J28:J37) -> 3349096.5 | ... N38: =SUM(N28:N37) -> 1542353.6
B40: =B18 -> Barter | C40: 2333333.3 | D40: 2333333.3 | E40: =28000000/12 -> 2333333.3 | F40: =28000000/12 -> 2333333.3 | G40: =28000000/12 -> 2333333.3 | H40: =28000000/12 -> 2333333.3 | I40: =28000000/12 -> 2333333.3 | J40: =28000000/12 -> 2333333.3 | K40: ='Dec-2025_IncomeStatement'!B14 -> 2246693.9 | L40: =28000000/12 -> 2333333.3 | M40: =28000000/12 -> 2333333.3 | N40: =28000000/12 -> 2333333.3
B42: Total (Incl Barter) | C42: =C38+C40 -> 4742528.3 | D42: =D38+D40 -> 4808325 | E42: =E38+E40 -> 5443045.1 | F42: =F38+F40 -> 4817041.3 | G42: =G38+G40 -> 5077813.4 | H42: =H38+H40 -> 5261304.9 | I42: =I38+I40 -> 5135338.9 | J42: =J38+J40 -> 5682429.9 | ... N42: =N38+N40 -> 3875686.9
B44: Weekly Inputs for Reconciliation:
B45: Adswizz Revenue | L45: ='Adswizz Rev_Exp_02.17'!D3 -> 37439.37 | M45: ='Adswizz Rev_Exp_02.17'!D14 -> 11298.24
B46: Adswizz Cost | L46: ='Adswizz Rev_Exp_02.17'!D6 -> 14105.29 | M46: ='Adswizz Rev_Exp_02.17'!D17 -> 2699.05
B47: Red Circle | L47: ='Programmatic Data_Michal_02.09'!B6 -> 44330.88 | M47: ='Programmatic Data_Michal_02.09'!L24 -> 12196.22
B48: Azerion | L48: 0 | M48: 0
B49: Audiohook | L49: 0 | M49: 0
B50: Triton | L50: ='Programmatic Data_Michal_02.09'!L16 -> 23504.98 | M50: ='Programmatic Data_Michal_02.09'!L23 -> 7230.03
B52: Art19 Gross Revenue | L52: ='Programmatic Data_Michal_02.09'!L14 -> 96456.837 | M52: 43375.69
A55: Prior Year History
A56: FY 2025 | B56: Calendar Year: | C56: 2024 | D56: 2024 | E56: 2024 | F56: 2024 | G56: 2024 | H56: 2024 | I56: 2024 | J56: 2024 | K56: 2024 | L56: 2025 | M56: 2025 | N56: 2025 | P56: =I56 -> 2024 | Q56: =J56 -> 2024 | R56: =K56 -> 2024 | S56: =L56 -> 2025
B57: PodcastOne - Gross Revenue
C58: Apr | D58: May | E58: Jun | F58: Jul | G58: Aug | H58: Sep | I58: Oct | J58: Nov | K58: Dec | L58: Jan | M58: Feb | N58: Mar | P58: Q1 | Q58: Q2 | R58: Q3 | S58: Q4 | T58: FY 2025 YTD
B59: BNB – Embedded Direct | C59: 1104.8429 | D59: 1441.4921 | E59: 1637.4337 | F59: 1213.7458 | G59: 1509.5396 | H59: 1320.5449 | I59: 1176.6899 | J59: 1613.0863 | K59: 1582.5122 | L59: 1164.2779 | M59: 1541.769 | N59: =1633.21443-(133804.19/1000) -> 1499.4102 | P59: =SUM(C59:E59) -> 4183.7688 | Q59: =SUM(F59:H59) -> 4043.8303 | R59: =SUM(I59:K59) -> 4372.2885 | S59: =SUM(L59:N59) -> 4205.4572 | T59: =SUM(P59:S59) -> 16805.345
B60: BNB – DAI Direct | C60: 189.64654 | D60: 194.86448 | E60: 248.88022 | F60: 223.79356 | G60: 146.72447 | H60: 293.15249 | I60: 291.68795 | J60: 271.39782 | K60: 241.03817 | L60: 201.36659 | M60: 224.25042 | N60: 220.63954 | P60: =SUM(C60:E60) -> 633.39124 | Q60: =SUM(F60:H60) -> 663.67052 | R60: =SUM(I60:K60) -> 804.12394 | S60: =SUM(L60:N60) -> 646.25655 | T60: =SUM(P60:S60) -> 2747.4423
B61: BNB – Other (social / segments / other) | C61: 0 | D61: 0 | E61: 0 | F61: 0 | G61: 0 | H61: 0 | I61: 0 | J61: 0 | K61: 0 | L61: 3 | M61: 34.5 | N61: 89.65 | P61: =SUM(C61:E61) -> 0 | Q61: =SUM(F61:H61) -> 0 | R61: =SUM(I61:K61) -> 0 | S61: =SUM(L61:N61) -> 127.15 | T61: =SUM(P61:S61) -> 127.15
B62: Programmatic Revenue | C62: 595.55221 | D62: 645.06832 | E62: 904.12662 | F62: 518.54318 | G62: 449.56198 | H62: 533.52292 | I62: 353.93539 | J62: 546.16159 | K62: 613.5406 | L62: 301.69411 | M62: 234.00315 | N62: 282.4851 | P62: =SUM(C62:E62) -> 2144.7472 | Q62: =SUM(F62:H62) -> 1501.6281 | R62: =SUM(I62:K62) -> 1513.6376 | S62: =SUM(L62:N62) -> 818.18236 | T62: =SUM(P62:S62) -> 5978.1952
B63: Art 19 - MG or billed | C63: 0 | D63: 0 | E63: 0 | F63: 0 | G63: 0 | H63: 0 | I63: 0 | J63: 0 | K63: 0 | L63: 0 | M63: 500 | N63: 228.04288 | P63: =SUM(C63:E63) -> 0 | Q63: =SUM(F63:H63) -> 0 | R63: =SUM(I63:K63) -> 0 | S63: =SUM(L63:N63) -> 728.04288 | T63: =SUM(P63:S63) -> 728.04288
B64: Podroll | C64: 0 | D64: 0 | E64: 0 | F64: 0 | G64: 0 | H64: 0 | I64: 0 | J64: 0 | K64: 0 | L64: 43.78144 | M64: 0 | N64: =(133804.19/1000) -> 133.80419 | P64: =SUM(C64:E64) -> 0 | Q64: =SUM(F64:H64) -> 0 | R64: =SUM(I64:K64) -> 0 | S64: =SUM(L64:N64) -> 177.58563 | T64: =SUM(P64:S64) -> 177.58563
B65: PodcastOne Pro | C65: 0 | D65: 0 | E65: 0 | F65: 0 | G65: 0 | H65: 0 | I65: 0 | J65: 0 | K65: 0 | L65: 0 | M65: 44 | N65: 21.75 | P65: =SUM(C65:E65) -> 0 | Q65: =SUM(F65:H65) -> 0 | R65: =SUM(I65:K65) -> 0 | S65: =SUM(L65:N65) -> 65.75 | T65: =SUM(P65:S65) -> 65.75
B66: Subscription Revenues | C66: 2.25538 | D66: 1.89196 | E66: 1.50066 | F66: 2.30837 | G66: 1.51313 | H66: 1.49816 | I66: 2.26723 | J66: 2.00356 | K66: 1.18239 | L66: 1.82768 | M66: 1.03979 | N66: 1.37813 | P66: =SUM(C66:E66) -> 5.648 | Q66: =SUM(F66:H66) -> 5.31966 | R66: =SUM(I66:K66) -> 5.45318 | S66: =SUM(L66:N66) -> 4.2456 | T66: =SUM(P66:S66) -> 20.66644
B67: Trade | C67: 0 | D67: 0 | E67: 0 | F67: 0 | G67: 0 | H67: 0 | I67: 0 | J67: 0 | K67: 0 | L67: 0 | M67: 0 | N67: 0 | P67: =SUM(C67:E67) -> 0 | Q67: =SUM(F67:H67) -> 0 | R67: =SUM(I67:K67) -> 0 | S67: =SUM(L67:N67) -> 0 | T67: =SUM(P67:S67) -> 0
B68: Other Revenues | C68: 23.34059 | D68: 35.13728 | E68: 132.63941 | F68: 50.87288 | G68: 66.53813 | H68: -178.32271 | I68: 2.77968 | J68: 1.40007 | K68: 10.2896 | L68: 3.30901 | M68: 0.86368 | N68: 266.17134 | P68: =SUM(C68:E68) -> 191.11728 | Q68: =SUM(F68:H68) -> -60.9117 | R68: =SUM(I68:K68) -> 14.46935 | S68: =SUM(L68:N68) -> 270.34403 | T68: =SUM(P68:S68) -> 415.01896
B69: Total (Excl Barter) | C69: =SUM(C59:C68) -> 1915.6377 | D69: =SUM(D59:D68) -> 2318.4542 | E69: =SUM(E59:E68) -> 2924.5806 | F69: =SUM(F59:F68) -> 2009.2638 | G69: =SUM(G59:G68) -> 2173.8773 | H69: =SUM(H59:H68) -> 1970.3958 | I69: =SUM(I59:I68) -> 1827.3602 | J69: =SUM(J59:J68) -> 2434.0493 | ... N69: =SUM(N59:N68) -> 2743.3314 | P69: =SUM(P59:P68) -> 7158.6725 | Q69: =SUM(Q59:Q68) -> 6153.5369 | R69: =SUM(R59:R68) -> 6709.9725 | S69: =SUM(S59:S68) -> 7043.0143 | T69: =SUM(T59:T68) -> 27065.196
B71: Barter | C71: 2286.8512 | D71: 2585.1593 | E71: 1127.9895 | F71: 2000 | G71: 2000 | H71: 2000 | I71: 2000 | J71: 2000 | K71: 2000 | L71: 2333.3333 | M71: 2333.3333 | N71: 2333.3333 | P71: 6000 | Q71: 6000 | R71: 6000 | S71: 7000 | T71: 25000
B73: Total (Incl Barter) | C73: =C69+C71 -> 4202.4889 | D73: =D69+D71 -> 4903.6135 | E73: =E69+E71 -> 4052.5701 | F73: =F69+F71 -> 4009.2638 | G73: =G69+G71 -> 4173.8773 | H73: =H69+H71 -> 3970.3958 | I73: =I69+I71 -> 3827.3602 | J73: =J69+J71 -> 4434.0493 | ... N73: =N69+N71 -> 5076.6648 | P73: =P69+P71 -> 13158.672 | Q73: =Q69+Q71 -> 12153.537 | R73: =R69+R71 -> 12709.972 | S73: =S69+S71 -> 14043.014 | T73: =T69+T71 -> 52065.196
A75: FY 2024 | B75: Calendar Year: | C75: 2023 | D75: 2023 | E75: 2023 | F75: 2023 | G75: 2023 | H75: 2023 | I75: 2023 | J75: 2023 | K75: 2023 | L75: 2024 | M75: 2024 | N75: 2024
B76: PodcastOne - Gross Revenue
C77: Apr | D77: May | E77: Jun | F77: Jul | G77: Aug | H77: Sep | I77: Oct | J77: Nov | K77: Dec | L77: Jan | M77: Feb | N77: Mar | P77: Q1 | Q77: Q2 | R77: Q3 | S77: Q4 | T77: FY 2024 YTD
B78: Podcast Ads (includes Act entries) | C78: 1022 | D78: 1552 | E78: 1429 | F78: 1240 | G78: 1600 | H78: 1524 | I78: 1532 | J78: 1950 | K78: 1647 | L78: 1200 | M78: 1311 | N78: 1511 | P78: 4003 | Q78: 4364 | R78: 5129 | S78: 4022 | T78: 17518
B79: Audiomax | C79: 759 | D79: 938 | E79: 812 | F79: 864 | G79: 848 | H79: 842 | I79: 721 | J79: 742 | K79: 643 | L79: 358 | M79: 516 | N79: 722 | P79: 2509 | Q79: 2554 | R79: 2106 | S79: 1596 | T79: 8765
B80: Premium | C80: 0 | D80: 0 | E80: 0 | F80: 0 | G80: 0 | H80: 0 | I80: 0 | J80: 0 | K80: 0 | L80: 0 | M80: 0 | N80: 0 | P80: 0 | Q80: 0 | R80: 0 | S80: 0 | T80: 0
B81: Motortrend | C81: 0 | D81: 0 | E81: 0 | F81: 0 | G81: 0 | H81: 0 | I81: 0 | J81: 74 | K81: 0 | L81: 38 | M81: 0 | N81: 0 | P81: 0 | Q81: 0 | R81: 74 | S81: 38 | T81: 112
B82: Live Shows | C82: 0 | D82: 0 | E82: 0 | F82: 0 | G82: 0 | H82: 0 | I82: 0 | J82: 0 | K82: 0 | L82: 0 | M82: 0 | N82: 0 | P82: 0 | Q82: 0 | R82: 0 | S82: 0 | T82: 0
B83: Merchandise | C83: 0 | D83: 0 | E83: 0 | F83: 0 | G83: 0 | H83: 0 | I83: 0 | J83: 0 | K83: 0 | L83: 0 | M83: 0 | N83: 0 | P83: 0 | Q83: 0 | R83: 0 | S83: 0 | T83: 0
B84: SCA | C84: 0 | D84: 0 | E84: 0 | F84: 0 | G84: 0 | H84: 0 | I84: 0 | J84: 0 | K84: 0 | L84: 0 | M84: 0 | N84: 0 | P84: 0 | Q84: 0 | R84: 0 | S84: 0 | T84: 0
B85: LXL Shared Deals | C85: 0 | D85: 0 | E85: 0 | F85: 0 | G85: 0 | H85: 0 | I85: 0 | J85: 0 | K85: 0 | L85: 0 | M85: 0 | N85: 0 | P85: 0 | Q85: 0 | R85: 0 | S85: 0 | T85: 0
B86: Total (Excl Barter) | C86: 1781 | D86: 2490 | E86: 2241 | F86: 2104 | G86: 2448 | H86: 2366 | I86: 2253 | J86: 2766 | K86: 2290 | L86: 1596 | M86: 1827 | N86: 2233 | P86: 6512 | Q86: 6918 | R86: 7309 | S86: 5656 | T86: 26395
B88: Barter | C88: 0 | D88: 0 | E88: 0 | F88: 0 | G88: 0 | H88: 0 | I88: 0 | J88: 0 | K88: 0 | L88: 2739.6117 | M88: 2446.5321 | N88: 813.85627 | P88: 0 | Q88: 0 | R88: 0 | S88: 6000 | T88: 6000
B90: Total (Incl Barter) | C90: 1781 | D90: 2490 | E90: 2241 | F90: 2104 | G90: 2448 | H90: 2366 | I90: 2253 | J90: 2766 | K90: 2290 | L90: 4335.6117 | M90: 4273.5321 | N90: 3046.8563 | P90: 6512 | Q90: 6918 | R90: 7309 | S90: 11656 | T90: 32395
A95: FY 2023 | C95: 2022 | D95: 2022 | E95: 2022 | F95: 2022 | G95: 2022 | H95: 2022 | I95: 2022 | J95: 2022 | K95: 2022 | L95: 2023 | M95: 2023 | N95: 2023
B96: PodcastOne - Gross Revenue
C97: Apr | D97: May | E97: Jun | F97: Jul | G97: Aug | H97: Sep | I97: Oct | J97: Nov | K97: Dec | L97: Jan | M97: Feb | N97: Mar | P97: Q1 | Q97: Q2 | R97: Q3 | S97: Q4 | T97: FY 2023 YTD
B98: Podcast Ads (includes Acctg entries) | C98: 1556.945 | D98: 1970.451 | E98: 2003.074 | F98: 1669.582 | G98: 1959.757 | H98: 1679.748 | I98: 1416.757 | J98: 1615.342 | K98: 1878.797 | L98: 1316.2412 | M98: 1103.473 | N98: 1810.2863 | P98: 5530.47 | Q98: 5309.087 | R98: 4910.896 | S98: 4230.0004 | T98: 19980.453
B99: Audiomax | C99: 544.757 | D99: 647.72 | E99: 626.747 | F99: 328.35784 | G99: 315.79702 | H99: 472.086 | I99: 395.646 | J99: 508.776 | K99: 430.65135 | L99: 216.317 | M99: 488.94263 | N99: 661.673 | P99: 1819.224 | Q99: 1116.2409 | R99: 1335.0734 | S99: 1366.9326 | T99: 5637.4708
B100: Premium | C100: 14 | D100: 19 | E100: 22 | F100: 14 | G100: 6 | H100: 33 | I100: 5 | J100: 21 | K100: 19 | L100: 17 | M100: 14 | N100: 10 | P100: 55 | Q100: 53 | R100: 45 | S100: 41 | T100: 194
B101: Motortrend | C101: 0 | D101: 0 | E101: 0 | F101: 100 | G101: 100 | H101: 0 | I101: 0 | J101: 0 | K101: 0 | L101: 0 | M101: 0 | N101: 0 | P101: 0 | Q101: 200 | R101: 0 | S101: 0 | T101: 200
B102: Live Shows | C102: 0 | D102: 0 | E102: 0 | F102: 0 | G102: 0 | H102: 0 | I102: 0 | J102: 0 | K102: 0 | L102: 0 | M102: 0 | N102: 0 | P102: 0 | Q102: 0 | R102: 0 | S102: 0 | T102: 0
B103: Merchandise | C103: 0 | D103: 0 | E103: 0 | F103: 0 | G103: 0 | H103: 0 | I103: 0 | J103: 0 | K103: 0 | L103: 0 | M103: 0 | N103: 0 | P103: 0 | Q103: 0 | R103: 0 | S103: 0 | T103: 0
B104: SCA | C104: 0 | D104: 0 | E104: 0 | F104: 0 | G104: 0 | H104: 0 | I104: 0 | J104: 0 | K104: 0 | L104: 0 | M104: 0 | N104: 0 | P104: 0 | Q104: 0 | R104: 0 | S104: 0 | T104: 0
B105: LXL Shared Deals | C105: 0 | D105: 0 | E105: 0 | F105: 0 | G105: 0 | H105: 0 | I105: 0 | J105: 0 | K105: 298 | L105: 0 | M105: 0 | N105: 0 | P105: 0 | Q105: 0 | R105: 298 | S105: 0 | T105: 298
B106: Total (Excl Barter) | C106: 2115.702 | D106: 2637.171 | E106: 2651.821 | F106: 2111.9398 | G106: 2381.554 | H106: 2184.834 | I106: 1817.403 | J106: 2145.118 | K106: 2626.4484 | L106: 1549.5582 | M106: 1606.4156 | N106: 2481.9593 | P106: 7404.694 | Q106: 6678.3279 | R106: 6588.9694 | S106: 5637.9331 | T106: 26309.924
B108: Barter | C108: 0 | D108: 0 | E108: 0 | F108: 0 | G108: 0 | H108: 0 | I108: 0 | J108: 0 | K108: 0 | L108: 666.66667 | M108: 1845.2744 | N108: 693.293 | P108: 0 | Q108: 0 | R108: 0 | S108: 3205.234 | T108: 3205.234
B110: Total (Incl Barter) | C110: 2115.702 | D110: 2637.171 | E110: 2651.821 | F110: 2111.9398 | G110: 2381.554 | H110: 2184.834 | I110: 1817.403 | J110: 2145.118 | K110: 2626.4484 | L110: 2216.2248 | M110: 3451.69 | N110: 3175.2523 | P110: 7404.694 | Q110: 6678.3279 | R110: 6588.9694 | S110: 8843.1671 | T110: 29515.158
A114: FY 2022 | C114: 2021 | D114: 2021 | E114: 2021 | F114: 2021 | G114: 2021 | H114: 2021 | I114: 2021 | J114: 2021 | K114: 2021 | L114: 2022 | M114: 2022 | N114: 2022
B115: PodcastOne - Gross Revenue
C116: Apr | D116: May | E116: Jun | F116: Jul | G116: Aug | H116: Sep | I116: Oct | J116: Nov | K116: Dec | L116: Jan | M116: Feb | N116: Mar | P116: Q1 | Q116: Q2 | R116: Q3 | S116: Q4 | T116: FY 2022 YTD
B117: Podcast Ads (includes Acctg entries) | C117: 1280.6774 | D117: 1616.7391 | E117: 1988.4876 | F117: 1843.2834 | G117: 2058.0352 | H117: 1816.332 | I117: 2026.4201 | J117: 2052.3354 | K117: 2067.5329 | L117: 1304.4697 | M117: 1781.8412 | N117: 2192.8976 | P117: 4885.904 | Q117: 5717.6507 | R117: 6146.2884 | S117: 5279.2086 | T117: 22029.052
B118: Audiomax | C118: 286.947 | D118: 426.36 | E118: 343.89288 | F118: 339.83501 | G118: 332.84335 | H118: 485.993 | I118: 499.566 | J118: 629.512 | K118: 744.774 | L118: 385.38431 | M118: 455.183 | N118: 556.28951 | P118: 1057.1999 | Q118: 1158.6714 | R118: 1873.852 | S118: 1396.8568 | T118: 5486.5801
B119: Premium | C119: 5 | D119: 5 | E119: 6 | F119: 5 | G119: 6 | H119: 4 | I119: 6 | J119: 5 | K119: 5 | L119: 19 | M119: 5 | N119: 100.9 | P119: 16 | Q119: 15 | R119: 16 | S119: 124.9 | T119: 171.9
B120: Motortrend | C120: 0 | D120: 0 | E120: 0 | F120: 0 | G120: 0 | H120: 0 | I120: 0 | J120: 0 | K120: 0 | L120: 0 | M120: 0 | N120: 0 | P120: 0 | Q120: 0 | R120: 0 | S120: 0 | T120: 0
B121: Live Shows | C121: 0 | D121: 0 | E121: 0 | F121: 0 | G121: 0 | H121: 0 | I121: 0 | J121: 0 | K121: 0 | L121: 0 | M121: 0 | N121: 0 | P121: 0 | Q121: 0 | R121: 0 | S121: 0 | T121: 0
B122: Merchandise | C122: 0 | D122: 0 | E122: 0 | F122: 0 | G122: 0 | H122: 0 | I122: 0 | J122: 0 | K122: 0 | L122: 0 | M122: 0 | N122: 0 | P122: 0 | Q122: 0 | R122: 0 | S122: 0 | T122: 0
B123: SCA | C123: 19 | D123: 19 | E123: 20 | F123: 0 | G123: 38 | H123: 20 | I123: 19 | J123: 19 | K123: 19 | L123: 0 | M123: 0 | N123: 0 | P123: 58 | Q123: 58 | R123: 57 | S123: 0 | T123: 173
B124: LXL Shared Deals | C124: 0 | D124: 0 | E124: 0 | F124: 0 | G124: 0 | H124: 0 | I124: 0 | J124: 0 | K124: 0 | L124: 0 | M124: 0 | N124: 0 | P124: 0 | Q124: 0 | R124: 0 | S124: 0 | T124: 0
B125: Total (Excl Barter) | C125: 1591.6244 | D125: 2067.0991 | E125: 2358.3805 | F125: 2188.1184 | G125: 2434.8786 | H125: 2326.325 | I125: 2550.9861 | J125: 2705.8474 | K125: 2836.3069 | L125: 1708.854 | M125: 2242.0242 | N125: 2850.0872 | P125: 6017.1039 | Q125: 6949.322 | R125: 8093.1404 | S125: 6800.9654 | T125: 27860.532
B127: Barter | C127: 474.65 | D127: 549 | E127: 524 | F127: 259 | G127: 551 | H127: 711 | I127: 0 | J127: 0 | K127: 0 | L127: 0 | M127: 0 | N127: 1249.0047 | P127: 1547.65 | Q127: 1521 | R127: 0 | S127: 1249.0047 | T127: 4317.6547
...

Sheet Variance Check
C3: 44927 | D3: =EDATE(C3,1) -> 44958 | E3: =EDATE(D3,1) -> 44986 | F3: =EDATE(E3,1) -> 45017 | G3: =EDATE(F3,1) -> 45047 | H3: =EDATE(G3,1) -> 45078 | I3: =EDATE(H3,1) -> 45108 | J3: =EDATE(I3,1) -> 45139 | K3: =EDATE(J3,1) -> 45170 | ... N3: =EDATE(M3,1) -> 45261
A4: Current | B4: Podcast Ads (BnB) | C4: =((148269+1199526)/0.85)-360000+90600 -> 1316241.2 | D4: =1453456-349983 -> 1103473 | E4: 1810286.3 | F4: =1289395.39-267800 -> 1021595.4 | G4: 1668664 | H4: 1602687 | I4: 1258506.2 | J4: 1078983.2 | K4: 881752.98 | L4: 679287.34 | M4: 802245.34 | N4: 644614.93
A5: Current | B5: Audiomax | C5: 216317 | D5: 488942.63 | E5: =1028522-366849 -> 661673 | F5: =978214-219055 -> 759159 | G5: =1241981-300719-2728 -> 938534 | H5: =730105-185741-1106 -> 543258
A7: Prior | B7: Podcast Ads (BnB) | C7: =((148269+1199526)/0.85)-360000+90600 -> 1316241.2 | D7: =1453456-349983 -> 1103473 | E7: 1810286.3 | F7: =1289395.39-267800 -> 1021595.4 | G7: 1668664 | H7: 1605194.4 | I7: 1557719.1 | J7: 1632111 | K7: 1303641.3 | L7: 1005655.6 | M7: 1070083.5 | N7: 840279.85
A8: Prior | B8: Audiomax | C8: 216317 | D8: 488942.63 | E8: =1028522-366849 -> 661673 | F8: =978214-219055 -> 759159 | G8: =1241981-300719-2728 -> 938534 | H8: =932277-229153-1780 -> 701344 | I8: =1101367-244521-2222 -> 854624 | J8: =233067-40195-549 -> 192323
A10: Difference | B10: Podcast Ads (BnB) | C10: =C4-C7 -> 0 | D10: =D4-D7 -> 0 | E10: =E4-E7 -> 0 | F10: =F4-F7 -> 0 | G10: =G4-G7 -> 0 | H10: =H4-H7 -> -2507.444 | I10: =I4-I7 -> -299212.87 | J10: =J4-J7 -> -553127.78 | ... N10: =N4-N7 -> -195664.92
B11: Audiomax | C11: =C5-C8 -> 0 | D11: =D5-D8 -> 0 | E11: =E5-E8 -> 0 | F11: =F5-F8 -> 0 | G11: =G5-G8 -> 0 | H11: =H5-H8 -> -158086 | I11: =I5-I8 -> -854624 | J11: =J5-J8 -> -192323 | ... N11: =N5-N8 -> 0
B16: Pacing - Yearly Summary
C17: Q1 | D17: Q2 | E17: Q3 | F17: Q4 | G17: Total | I17: ME CLOSE | J17: -36.7 | K17: Adswizz
B18: Prior Week Input | C18: 7993.8984 | D18: 8156.1595 | E18: 8942.3971 | F18: 5427.4891 | G18: 30519.944 | J18: =-20-20 -> -40 | K18: BnB
B20: Week overWeek Changes | C20: ='Pacing - Yearly Summary'!C16-C18 -> 0 | D20: ='Pacing - Yearly Summary'!D16-D18 -> 0 | E20: ='Pacing - Yearly Summary'!E16-E18 -> 0 | F20: ='Pacing - Yearly Summary'!F16-F18 -> 0 | G20: ='Pacing - Yearly Summary'!G16-G18 -> 0
B24: Pacing - Act. vs Budget | P24: sheet 1 | Q24: confirm with kit this view is OK
C26: Q1 | D26: Q2 | E26: Q3 | F26: Q4 | G26: Total | P26: sheet 2 | Q26: update the budget with the revised numbers on the street
B27: Prior Week Input | C27: 7993.8984 | D27: 8156.1595 | E27: 8942.3971 | F27: 5427.4891 | G27: 30519.944
P28: sheet 3 | Q28: get the q1 forecasts from everyone
B29: Week overWeek Changes | C29: ='Pacing - Act. vs Budget'!C17-C27 -> 0 | D29: ='Pacing - Act. vs Budget'!D17-D27 -> 0 | E29: ='Pacing - Act. vs Budget'!E17-E27 -> 0 | F29: ='Pacing - Act. vs Budget'!F17-F27 -> 0 | G29: ='Pacing - Act. vs Budget'!G17-G27 -> 0
F31: 0 | G31: Programmatic | H31: =SUM(C29:F29)-F31 -> 0 | I31: billednbooked
B33: Pacing - Monthly Inputs (actuals)
C34: Apr | D34: May | E34: Jun | F34: Jul | G34: Aug | H34: Sep | I34: Oct | J34: Nov | K34: Dec | L34: Jan | M34: Feb | N34: Mar
B35: Prior Week Input | C35: 2409.195 | D35: 2474.9917 | E35: 3109.7117 | F35: 2483.7079 | G35: 2744.48 | H35: 2927.9715 | I35: 2802.0056 | J35: 3349.0965 | K35: 2791.295 | L35: 2087.2233 | M35: 1797.9122 | N35: 1542.3536
B37: Week overWeek Changes | C37: ='Pacing - Monthly Inputs (actual'!C16-C35 -> 0 | D37: ='Pacing - Monthly Inputs (actual'!D16-D35 -> 0 | E37: ='Pacing - Monthly Inputs (actual'!E16-E35 -> 0 | F37: ='Pacing - Monthly Inputs (actual'!F16-F35 -> 0 | G37: ='Pacing - Monthly Inputs (actual'!G16-G35 -> 0 | H37: ='Pacing - Monthly Inputs (actual'!H16-H35 -> 0 | I37: ='Pacing - Monthly Inputs (actual'!I16-I35 -> 0 | J37: ='Pacing - Monthly Inputs (actual'!J16-J35 -> 0 | ... N37: ='Pacing - Monthly Inputs (actual'!N16-N35 -> 0 | O37: =SUM(C37:N37) -> 0
B40: Reference Guide:
B41: BNB – Embedded Direct | C41: Phil
B42: BNB – DAI Direct | C42: Phil
B43: BNB – Other (social / segments / other) | C43: Phil
B44: Programmatic Revenue | C44: Ellie | E44: Programmatic Revenue
B45: Art 19 - MG or billed | C45: Ellie | E45: Art 19 - MG or billed
B46: Podroll | C46: Michal | E46: Subscription Revenues
B47: PodcastOne Pro | C47: (Jim L. / Alistair
B48: Subscription Revenues | C48: Ellie
B49: Trade | C49: Phil
B50: Other Revenues | C50: N/A

Sheet Forecast Supports -->

Sheet Adswizz Rev_Exp_02.17
A1: Revenue
A2: Start Date | B2: End Date | C2: Net Revenue | D2: Gross Revenue | E2: Impressions
A3: 46023 | B3: 46053 | C3: 29159.23 | D3: 37439.37 | E3: 4505347
A5: Cost
A6: 46023 | B6: 46053 | C6: 9873.7 | D6: 14105.29 | E6: 1363995
A8: Net Total
A9: 46023 | B9: 46053 | C9: =C3-C6 -> 19285.53 | D9: =D3-D6 -> 23334.08 | E9: =E3-E6 -> 3141352
A12: Revenue
A13: Start Date | B13: End Date | C13: Net Revenue | D13: Gross Revenue | E13: Impressions
A14: 46054 | B14: 46062 | C14: 9030.25 | D14: 11298.24 | E14: 1555729
A16: Cost
A17: 46054 | B17: 46062 | C17: 2307.68 | D17: 2699.05 | E17: 385900
A19: Net Total
A20: 46054 | B20: 46062 | C20: =C14-C17 -> 6722.57 | D20: =D14-D17 -> 8599.19 | E20: =E14-E17 -> 1169829

Sheet Programmatic Data_Michal_02.09
B1: JAN | C1: FEB | D1: MARCH | E1: APRIL | F1: MAY | G1: JUNE | H1: JULY | I1: AUGUST | J1: SEPTEMBER | K1: OCTOBER | L1: NOVEMBER | M1: DECEMBER | O1: Links
A2: Gross Capacity | B2: 106m
A3: ART19 | B3: =L14 -> 96456.837 | C3: =L21 -> 42368.567 | D3: =L28 -> 0 | E3: =L35 -> 0 | F3: =L42 -> 0 | G3: =L49 -> 0 | H3: =L56 -> 0 | I3: =L63 -> 0 | J3: =L70 -> 0 | K3: =L77 -> 0 | L3: =L84 -> 0 | M3: =L91 -> 0 | O3: https://app.mode.com/art19_test/reports/047fccb7e999?secret_key=512e37693bbda22d23343493
A4: AudioMax (gross) | B4: =L15 -> 37439.36 | C4: =L22 -> 10206.88 | D4: =L29 -> 0 | E4: =L36 -> 0 | F4: =L43 -> 0 | G4: =L50 -> 0 | H4: =L57 -> 0 | I4: =L64 -> 0 | J4: =L71 -> 0 | K4: =L78 -> 0 | L4: =L85 -> 0 | M4: =L92 -> 0 | O4: https://audiomax.adswizz.com/podcastone/revenue/salesChannels?status=ACTIVE&status=ABOUT_TO_EXPIRE&status=ABOUT_TO_START
A5: Triton | B5: =L16 -> 23504.98 | C5: =L23 -> 7230.03 | D5: =L30 -> 0 | E5: =L37 -> 0 | F5: =L44 -> 0 | G5: =L51 -> 0 | H5: =L58 -> 0 | I5: =L65 -> 0 | J5: =L73 -> 0 | K5: =L80 -> 0 | L5: =L87 -> 0 | M5: =L94 -> 0 | O5: https://app.redcircle.com/shows
A6: Red Circle (grossed Up/estimates) | B6: =L17 -> 44330.88 | C6: =L24 -> 12196.22 | D6: =L31 -> 0 | E6: =L38 -> 0 | F6: =L45 -> 0 | G6: =L52 -> 0 | H6: =L59 -> 0 | I6: =L66 -> 0 | J6: =L72 -> 0 | K6: =L79 -> 0 | L6: =L86 -> 0 | M6: =L93 -> 0 | O6: https://podcastone.manadge.tritondigital.com/dashboard | P6: Login | Q6: michal@Podcastone.com | R6: 9sryCknH!7RcKg9
A7: Audiohook | B7: 757.84 | O7: https://publishers.audiohook.com/podcastone/account-details
A9: TOTAL Gross | B9: =SUM(B3:B8) -> 202489.9 | C9: =SUM(C3:C8) -> 72001.697 | D9: =SUM(D3:D8) -> 0 | E9: =SUM(E3:E8) -> 0 | F9: =SUM(F3:F8) -> 0 | G9: =SUM(G3:G8) -> 0 | H9: =SUM(H3:H8) -> 0 | I9: =SUM(I3:I8) -> 0 | ... M9: =SUM(M3:M8) -> 0 | N9: =SUM(B9:M9) -> 274491.59 | O9: =N9/N10 -> 0.041765546
A10: 2025 TOTAL | B10: 302474 | C10: 219092 | D10: 506260 | E10: 601232.02 | F10: 636197.26 | G10: 686808.2 | H10: 722732.03 | I10: 813754.2 | J10: 804377.98 | K10: 611670.69 | L10: 667603.31 | N10: =SUM(B10:M10) -> 6572201.7
A12: JAN | B12: 1/1 - 1/4 | D12: 45662 | F12: 45669 | H12: 45676 | J12: 1/26 - 1/31
B13: Net | C13: Gross | D13: Net | E13: Gross | F13: Net | G13: Gross | H13: Net | I13: Gross | J13: Net | K13: Gross | L13: Gross | N13: 22165.44
A14: ART19 | B14: 6469.6 | C14: =B14/0.6 -> 10782.667 | E14: 18449 | G14: 22282 | I14: 22199.97 | K14: 22743.2 | L14: =SUM(E14+G14+I14+K14+C14) -> 96456.837 | N14: 17056.59 | P14: RAP Programmatic | Q14: 46047 | R14: 656.51
A15: AudioMax | B15: 3457.34 | C15: 4582.56 | D15: 6649.03 | E15: 8609.12 | F15: 6784.5 | G15: 8725.15 | H15: 6218.08 | I15: 7880.32 | J15: 6050.28 | K15: 7642.21 | L15: =SUM(E15+G15+I15+K15+C15) -> 37439.36 | N15: =N13-N14 -> 5108.85 | P15: RAP Programmatic | Q15: 46046 | R15: 698.87
A16: Triton | C16: 1835.91 | E16: 4948.41 | G16: 5071.69 | I16: 5980.68 | K16: 5668.29 | L16: =SUM(E16+G16+I16+K16+C16) -> 23504.98 | P16: RAP Programmatic | Q16: 46045 | R16: 747.45
A17: Red Circle | B17: 2362.16 | C17: =B17*2 -> 4724.32 | D17: 3400.3 | E17: =D17*2 -> 6800.6 | F17: 5311.78 | G17: =F17*2 -> 10623.56 | H17: 5982.35 | I17: =H17*2 -> 11964.7 | J17: 5108.85 | K17: =J17*2 -> 10217.7 | L17: =SUM(E17+G17+I17+K17+C17) -> 44330.88 | P17: RAP Programmatic | Q17: 46044 | R17: 922.84
P18: RAP Programmatic | Q18: 46043 | R18: 949.89
A19: FEB | B19: 45689 | D19: 45690 | F19: 45697 | H19: 45704 | J19: 2/23 - 2/28 | L19: FEb | N19: 22165.44 | P19: RAP Programmatic | Q19: 46042 | R19: 1171.69
B20: Net | C20: Gross | D20: Net | E20: Gross | F20: Net | G20: Gross | H20: Net | I20: Gross | J20: Net | K20: Gross | L20: Gross | N20: 17056.59 | P20: RAP Programmatic | Q20: 46041 | R20: 835.1
A21: ART19 | C21: =B21/0.6 -> 0 | D21: 25421.14 | E21: =D21/0.6 -> 42368.567 | G21: =F21/0.6 -> 0 | I21: =H21/0.6 -> 0 | K21: =J21/0.6 -> 0 | L21: =SUM(E21+G21+I21+K21+C21) -> 42368.567 | N21: =N19-N20 -> 5108.85 | R21: =SUM(R14:R20) -> 5982.35
A22: AudioMax | D22: 8159.24 | E22: 10206.88 | L22: =SUM(E22+G22+I22+K22+C22) -> 10206.88
A23: Triton | E23: 7230.03 | L23: =SUM(E23+G23+I23+K23+C23) -> 7230.03
A24: Red Circle | C24: =B24*2 -> 0 | D24: 6098.11 | E24: =D24*2 -> 12196.22 | G24: =F24*2 -> 0 | I24: =H24*2 -> 0 | K24: =J24*2 -> 0 | L24: =SUM(E24+G24+I24+K24+C24) -> 12196.22
A26: MARCH | B26: 3/1 - 3/8 | D26: 45725 | F26: 45732 | H26: 45739 | J26: 3/30 -3/31 | L26: March
B27: Net | C27: Gross | D27: Net | E27: Gross | F27: Net | G27: Gross | H27: Net | I27: Gross | J27: Net | K27: Gross
A28: ART19 | C28: =B28/0.6 -> 0 | E28: =D28/0.6 -> 0 | G28: =F28/0.6 -> 0 | I28: =H28/0.6 -> 0 | K28: =J28/0.6 -> 0 | L28: =SUM(E28+G28+I28+K28+C28) -> 0
A29: AudioMax | L29: =SUM(E29+G29+I29+K29+C29) -> 0
A30: Triton | L30: =SUM(E30+G30+I30+K30+C30) -> 0
A31: Red Circle | C31: =B31*2 -> 0 | E31: =D31*2 -> 0 | G31: =F31*2 -> 0 | I31: =H31*2 -> 0 | K31: =J31*2 -> 0 | L31: =SUM(E31+G31+I31+K31+C31) -> 0
A33: APRIL | B33: 4/1 - 4/5 | D33: 45753 | F33: 45760 | H33: 45767 | J33: 4/27 - 4/30
B34: Net | C34: Gross | D34: Net | E34: Gross | F34: Net | G34: Gross | H34: Net | I34: Gross | J34: Net | K34: Gross
A35: ART19 | C35: =B35/0.6 -> 0 | E35: =D35/0.6 -> 0 | G35: =F35/0.6 -> 0 | I35: =H35/0.6 -> 0 | K35: =J35/0.6 -> 0 | L35: =SUM(E35+G35+I35+K35+C35) -> 0
A36: AudioMax | L36: =SUM(E36+G36+I36+K36+C36) -> 0
A37: Triton | L37: =SUM(E37+G37+I37+K37+C37) -> 0
A38: Red Circle | C38: =B38*2 -> 0 | E38: =D38*2 -> 0 | G38: =F38*2 -> 0 | I38: =H38*2 -> 0 | K38: =J38*2 -> 0 | L38: =SUM(E38+G38+I38+K38+C38) -> 0
A40: MAY | B40: 5/1 - 5/3 | D40: 45781 | F40: 45788 | H40: 45795 | J40: 45802
B41: Net | C41: Gross | D41: Net | E41: Gross | F41: Net | G41: Gross | H41: Net | I41: Gross | J41: Net | K41: Gross
A42: ART19 | C42: =B42/0.6 -> 0 | E42: =D42/0.6 -> 0 | G42: =F42/0.6 -> 0 | I42: =H42/0.6 -> 0 | K42: =J42/0.6 -> 0 | L42: =SUM(E42+G42+I42+K42+C42) -> 0
A43: AudioMax | L43: =SUM(E43+G43+I43+K43+C43) -> 0
A44: Triton | L44: =SUM(E44+G44+I44+K44+C44) -> 0
A45: Red Circle | C45: =B45*2 -> 0 | E45: =D45*2 -> 0 | G45: =F45*2 -> 0 | I45: =H45*2 -> 0 | K45: =J45*2 -> 0 | L45: =SUM(E45+G45+I45+K45+C45) -> 0
A47: JUNE | B47: 45809 | D47: 45816 | F47: 45823 | H47: 45830 | J47: 6/29 - 6/30
B48: Net | C48: Gross | D48: Net | E48: Gross | F48: Net | G48: Gross | H48: Net | I48: Gross | J48: Net | K48: Gross
A49: ART19 | C49: =B49/0.6 -> 0 | E49: =D49/0.6 -> 0 | G49: =F49/0.6 -> 0 | I49: =H49/0.6 -> 0 | K49: =J49/0.6 -> 0 | L49: =SUM(E49+G49+I49+K49+C49) -> 0
A50: AudioMax | L50: =SUM(E50+G50+I50+K50+C50) -> 0
A51: Triton | L51: =SUM(E51+G51+I51+K51+C51) -> 0
A52: Red Circle | C52: =B52*2 -> 0 | E52: =D52*2 -> 0 | G52: =F52*2 -> 0 | I52: =H52*2 -> 0 | K52: =J52*2 -> 0 | L52: =SUM(E52+G52+I52+K52+C52) -> 0
A54: JULY | B54: 7/1 - 7/5 | D54: 45844 | F54: 45851 | H54: 45858 | J54: 7/27 - 7/31
B55: Net | C55: Gross | D55: Net | E55: Gross | F55: Net | G55: Gross | H55: Net | I55: Gross | J55: Net | K55: Gross
A56: ART19 | C56: =B56/0.6 -> 0 | E56: =D56/0.6 -> 0 | G56: =F56/0.6 -> 0 | I56: =H56/0.6 -> 0 | K56: =J56/0.6 -> 0 | L56: =SUM(E56+G56+I56+K56+C56) -> 0
A57: AudioMax | L57: =SUM(E57+G57+I57+K57+C57) -> 0
A58: Triton | L58: =SUM(E58+G58+I58+K58+C58) -> 0
A59: Red Circle | C59: =B59*2 -> 0 | E59: =D59*2 -> 0 | G59: =F59*2 -> 0 | I59: =H59*2 -> 0 | K59: =J59*2 -> 0 | L59: =SUM(E59+G59+I59+K59+C59) -> 0
A61: AUGUST | B61: 8/1 - 8/2 | D61: 45872 | F61: 45879 | H61: 45886 | J61: 8/24 - 8/31
B62: Net | C62: Gross | D62: Net | E62: Gross | F62: Net | G62: Gross | H62: Net | I62: Gross | J62: Net | K62: Gross | L62: August
A63: ART19 | C63: =B63/0.6 -> 0 | E63: =D63/0.6 -> 0 | G63: =F63/0.6 -> 0 | I63: =H63/0.6 -> 0 | K63: =J63/0.6 -> 0 | L63: =SUM(E63+G63+I63+K63+C63) -> 0
A64: AudioMax | L64: =SUM(E64+G64+I64+K64+C64) -> 0
A65: Triton | L65: =SUM(E65+G65+I65+K65+C65) -> 0
A66: Red Circle | C66: =B66*2 -> 0 | E66: =D66*2 -> 0 | G66: =F66*2 -> 0 | I66: =H66*2 -> 0 | K66: =J66*2 -> 0 | L66: =SUM(E66+G66+I66+K66+C66) -> 0
A68: SEPTEMBER | B68: 9/1 - 9/6 | D68: 45907 | F68: 45914 | H68: 45921 | J68: 9/28 - 9/30 | L68: September
B69: Net | C69: Gross | D69: Net | E69: Gross | F69: Net | G69: Gross | H69: Net | I69: Gross | J69: Net | K69: Gross | L69: Gross
A70: ART19 | C70: =B70/0.6 -> 0 | E70: =D70/0.6 -> 0 | G70: =F70/0.6 -> 0 | I70: =H70/0.6 -> 0 | K70: =J70/0.6 -> 0 | L70: =SUM(E70+G70+I70+K70+C70) -> 0
A71: AudioMax | L71: =SUM(E71+G71+I71+K71+C71) -> 0
A72: Triton | L72: =SUM(E72+G72+I72+K72+C72) -> 0
A73: Red Circle | C73: =B73*2 -> 0 | E73: =D73*2 -> 0 | G73: =F73*2 -> 0 | I73: =H73*2 -> 0 | K73: =J73*2 -> 0 | L73: =SUM(E73+G73+I73+K73+C73) -> 0
A75: OCTOBER | B75: 10/1 - 10/4 | D75: 45935 | F75: 45942 | H75: 45949 | J75: 45956 | L75: October
B76: Net | C76: Gross | D76: Net | E76: Gross | F76: Net | G76: Gross | H76: Net | I76: Gross | J76: Net | K76: Gross | L76: Gross
A77: ART19 | C77: =B77/0.6 -> 0 | E77: =D77/0.6 -> 0 | G77: =F77/0.6 -> 0 | I77: =H77/0.6 -> 0 | K77: =J77/0.6 -> 0 | L77: =SUM(E77+G77+I77+K77+C77) -> 0
A78: AudioMax | L78: =SUM(E78+G78+I78+K78+C78) -> 0
A79: Triton | L79: =SUM(E79+G79+I79+K79+C79) -> 0
A80: Red Circle | C80: =B80*2 -> 0 | E80: =D80*2 -> 0 | G80: =F80*2 -> 0 | I80: =H80*2 -> 0 | K80: =J80*2 -> 0 | L80: =SUM(E80+G80+I80+K80+C80) -> 0 | N80: 45310.26 | O80: =N80-L80 -> 45310.26
A82: NOVEMBER | B82: 11/1 - 11/8 | D82: 45970 | F82: 45977 | H82: 45984 | J82: 45991 | L82: November
B83: Net | C83: Gross | D83: Net | E83: Gross | F83: Net | G83: Gross | H83: Net | I83: Gross | J83: Net | K83: Gross | L83: Gross
A84: ART19 | C84: =B84/0.6 -> 0 | E84: =D84/0.6 -> 0 | G84: =F84/0.6 -> 0 | I84: =H84/0.6 -> 0 | K84: =J84/0.6 -> 0 | L84: =SUM(E84+G84+I84+K84+C84) -> 0
A85: AudioMax | L85: =SUM(E85+G85+I85+K85+C85) -> 0
A86: Triton | L86: =SUM(E86+G86+I86+K86+C86) -> 0
A87: Red Circle | C87: =B87*2 -> 0 | E87: =D87*2 -> 0 | G87: =F87*2 -> 0 | I87: =H87*2 -> 0 | K87: =J87*2 -> 0 | L87: =SUM(E87+G87+I87+K87+C87) -> 0
A89: DECEMBER | B89: 12/1 - 12/6 | D89: 45998 | F89: 46005 | H89: 46012 | J89: 12/28 - 12/31 | L89: December
B90: Net | C90: Gross | D90: Net | E90: Gross | F90: Net | G90: Gross | H90: Net | I90: Gross | J90: Net | K90: Gross | L90: Gross
A91: ART19 | C91: =B91/0.6 -> 0 | E91: =D91/0.6 -> 0 | G91: =F91/0.6 -> 0 | I91: =H91/0.6 -> 0 | K91: =J91/0.6 -> 0 | L91: =SUM(E91+G91+I91+K91+C91) -> 0
A92: AudioMax | L92: =SUM(E92+G92+I92+K92+C92) -> 0
A93: Triton | L93: =SUM(E93+G93+I93+K93+C93) -> 0
A94: Red Circle | C94: =B94*2 -> 0 | E94: =D94*2 -> 0 | G94: =F94*2 -> 0 | I94: =H94*2 -> 0 | K94: =J94*2 -> 0 | L94: =SUM(E94+G94+I94+K94+C94) -> 0

Sheet Billed n Booked_Philip_02.02
A1: 15 | B1: Product | C1: 46023 | D1: 46054 | E1: 45717 | F1: 46113 | G1: 46143 | H1: 46174 | I1: 46204 | J1: 46235 | K1: 46266 | L1: 46296 | M1: 46327 | N1: 46357 | O1: Q1 | P1: Q2 | Q1: Q3 | R1: Q4 | S1: Total
A2: Podcast | B2: Adam Carolla Show | C2: 133119.36 | D2: 102909.11 | E2: 86865.99 | F2: 48803.26 | G2: 45144.68 | H2: 46172.65 | I2: 41944.68 | J2: 51582.51 | K2: 44834.83 | L2: 49094.08 | M2: 51691.68 | N2: 39290.11 | O2: =SUM(C2:E2) -> 322894.46 | P2: =SUM(F2:H2) -> 140120.59 | Q2: =SUM(I2:K2) -> 138362.02 | R2: =SUM(L2:N2) -> 140075.87 | S2: =SUM(C2:N2) -> 741452.94
A3: Podcast | B3: American Justice | C3: 1050 | D3: 0 | E3: 1050 | O3: =SUM(C3:E3) -> 2100 | P3: =SUM(F3:H3) -> 0 | Q3: =SUM(I3:K3) -> 0 | R3: =SUM(L3:N3) -> 0 | S3: =SUM(C3:N3) -> 2100
A4: Podcast | B4: Barely Famous with Kail Lowry | C4: 45733.39 | D4: 34429.4 | E4: 33383.4 | F4: 16473.9 | G4: 12973.9 | H4: 14723.9 | I4: 14723.9 | J4: 14723.9 | K4: 12973.9 | L4: 16523.9 | M4: 16523.9 | N4: 13148.9 | O4: =SUM(C4:E4) -> 113546.19 | P4: =SUM(F4:H4) -> 44171.7 | Q4: =SUM(I4:K4) -> 42421.7 | R4: =SUM(L4:N4) -> 46196.7 | S4: =SUM(C4:N4) -> 246336.29
A5: Podcast | B5: Beach Too Sandy Water Too Wet | C5: 12004.06 | D5: 9561.06 | E5: 8281.06 | F5: 4167.02 | G5: 3417.02 | H5: 3417.02 | I5: 4167.02 | J5: 3417.02 | K5: 4847.02 | L5: 3417.02 | M5: 4167.02 | N5: 3417.02 | O5: =SUM(C5:E5) -> 29846.18 | P5: =SUM(F5:H5) -> 11001.06 | Q5: =SUM(I5:K5) -> 12431.06 | R5: =SUM(L5:N5) -> 11001.06 | S5: =SUM(C5:N5) -> 64279.36
A6: Podcast | B6: Bitch Bible | C6: 32796.49 | D6: 30691.49 | E6: 26991.49 | F6: 19731.49 | G6: 21231.49 | H6: 19731.49 | I6: 23356.49 | J6: 18531.49 | K6: 22431.49 | L6: 18531.49 | M6: 20117.21 | N6: 18720.78 | O6: =SUM(C6:E6) -> 90479.47 | P6: =SUM(F6:H6) -> 60694.47 | Q6: =SUM(I6:K6) -> 64319.47 | R6: =SUM(L6:N6) -> 57369.48 | S6: =SUM(C6:N6) -> 272862.89
A7: Podcast | B7: BroadSide | C7: 1400 | D7: 0 | E7: 1400 | O7: =SUM(C7:E7) -> 2800 | P7: =SUM(F7:H7) -> 0 | Q7: =SUM(I7:K7) -> 0 | R7: =SUM(L7:N7) -> 0 | S7: =SUM(C7:N7) -> 2800
A8: Podcast | B8: Camp Counselors | C8: 7210.5 | D8: 4510.5 | E8: 6260.5 | F8: 4510.5 | G8: 4510.5 | H8: 4510.5 | I8: 4510.5 | J8: 4510.5 | K8: 4510.5 | L8: 4510.5 | M8: 4510.5 | N8: 4510.5 | O8: =SUM(C8:E8) -> 17981.5 | P8: =SUM(F8:H8) -> 13531.5 | Q8: =SUM(I8:K8) -> 13531.5 | R8: =SUM(L8:N8) -> 13531.5 | S8: =SUM(C8:N8) -> 58576
A9: Podcast | B9: Cate and Ty | C9: 8513.5 | D9: 3613.5 | E9: 11513.5 | F9: 5113.5 | G9: 5113.5 | H9: 5113.5 | I9: 5113.5 | J9: 3613.5 | K9: 3613.5 | L9: 3613.5 | M9: 3613.5 | N9: 3613.5 | O9: =SUM(C9:E9) -> 23640.5 | P9: =SUM(F9:H9) -> 15340.5 | Q9: =SUM(I9:K9) -> 12340.5 | R9: =SUM(L9:N9) -> 10840.5 | S9: =SUM(C9:N9) -> 62162
A10: Podcast | B10: Chrisley Confessions | C10: 68541.07 | D10: 60045.06 | E10: 48143.06 | F10: 39945.06 | G10: 20395.06 | H10: 24645.06 | I10: 24645.06 | J10: 28895.06 | K10: 20395.06 | L10: 24645.06 | M10: 29645.06 | N10: 6897.06 | O10: =SUM(C10:E10) -> 176729.19 | P10: =SUM(F10:H10) -> 84985.18 | Q10: =SUM(I10:K10) -> 73935.18 | R10: =SUM(L10:N10) -> 61187.18 | S10: =SUM(C10:N10) -> 396836.73
A11: Podcast | B11: City Confidential | C11: 1050 | D11: 0 | E11: 1050 | O11: =SUM(C11:E11) -> 2100 | P11: =SUM(F11:H11) -> 0 | Q11: =SUM(I11:K11) -> 0 | R11: =SUM(L11:N11) -> 0 | S11: =SUM(C11:N11) -> 2100
A12: Podcast | B12: Coffee Convos | C12: 52089.8 | D12: 43987 | E12: 54564.8 | F12: 23212 | G12: 19169.8 | H12: 19812 | I12: 22144.8 | J12: 19812 | K12: 22144.8 | L12: 19812 | M12: 22144.8 | N12: 19812 | O12: =SUM(C12:E12) -> 150641.6 | P12: =SUM(F12:H12) -> 62193.8 | Q12: =SUM(I12:K12) -> 64101.6 | R12: =SUM(L12:N12) -> 61768.8 | S12: =SUM(C12:N12) -> 338705.8
A13: Podcast | B13: Cold Case Files | C13: 62238.24 | D13: 51520.99 | E13: 62420.99 | F13: 23719.49 | G13: 19752.24 | H13: 19752.24 | I13: 23719.49 | J13: 19752.24 | K13: 19752.24 | L13: 23719.49 | M13: 23152.24 | N13: 18780.81 | O13: =SUM(C13:E13) -> 176180.22 | P13: =SUM(F13:H13) -> 63223.97 | Q13: =SUM(I13:K13) -> 63223.97 | R13: =SUM(L13:N13) -> 65652.54 | S13: =SUM(C13:N13) -> 368280.7
A14: Podcast | B14: Court Junkie | C14: 12920 | D14: 12970 | E14: 15590 | F14: 6670 | G14: 4200 | H14: 6070 | I14: 4270 | J14: 7940 | K14: 6070 | L14: 4270 | M14: 4200 | N14: 4270 | O14: =SUM(C14:E14) -> 41480 | P14: =SUM(F14:H14) -> 16940 | Q14: =SUM(I14:K14) -> 18280 | R14: =SUM(L14:N14) -> 12740 | S14: =SUM(C14:N14) -> 89440
A15: Podcast | B15: Delusional Diaries | C15: 6188 | D15: 5225 | E15: 5763 | F15: 1375 | G15: 925 | H15: 925 | I15: 1375 | J15: 925 | K15: 1375 | L15: 925 | M15: 1375 | N15: 925 | O15: =SUM(C15:E15) -> 17176 | P15: =SUM(F15:H15) -> 3225 | Q15: =SUM(I15:K15) -> 3675 | R15: =SUM(L15:N15) -> 3225 | S15: =SUM(C15:N15) -> 27301
A16: Podcast | B16: Detox Retox | C16: 910 | D16: 250 | E16: 910 | F16: 250 | G16: 250 | H16: 250 | I16: 250 | J16: 250 | K16: 250 | L16: 250 | M16: 250 | N16: 250 | O16: =SUM(C16:E16) -> 2070 | P16: =SUM(F16:H16) -> 750 | Q16: =SUM(I16:K16) -> 750 | R16: =SUM(L16:N16) -> 750 | S16: =SUM(C16:N16) -> 4320
A17: Podcast | B17: Dumb Gay Podcast | C17: 200 | D17: 400 | E17: 0 | F17: 400 | G17: 200 | H17: 200 | I17: 200 | J17: 200 | K17: 200 | L17: 200 | M17: 200 | N17: 200 | O17: =SUM(C17:E17) -> 600 | P17: =SUM(F17:H17) -> 800 | Q17: =SUM(I17:K17) -> 600 | R17: =SUM(L17:N17) -> 600 | S17: =SUM(C17:N17) -> 2600
A18: Podcast | B18: Fool Coverage | C18: 22565 | D18: 24840 | E18: 12840 | F18: 12800 | G18: 6525 | H18: 8550 | I18: 10550 | J18: 8550 | K18: 6525 | L18: 10550 | M18: 8550 | N18: 6525 | O18: =SUM(C18:E18) -> 60245 | P18: =SUM(F18:H18) -> 27875 | Q18: =SUM(I18:K18) -> 25625 | R18: =SUM(L18:N18) -> 25625 | S18: =SUM(C18:N18) -> 139370
A19: Podcast | B19: IHIP News | C19: 92762.61 | D19: 93387.61 | E19: 88287.61 | F19: 63312.61 | G19: 63312.61 | H19: 63312.61 | I19: 63312.61 | J19: 63312.61 | O19: =SUM(C19:E19) -> 274437.83 | P19: =SUM(F19:H19) -> 189937.83 | Q19: =SUM(I19:K19) -> 126625.22 | R19: =SUM(L19:N19) -> 0 | S19: =SUM(C19:N19) -> 591000.88
A20: Podcast | B20: I Survived | C20: 25463.23 | D20: 16161.46 | E20: 25961.46 | F20: 7128.23 | G20: 10161.46 | H20: 4095 | I20: 7128.23 | J20: 10161.46 | K20: 7128.23 | L20: 10161.46 | M20: 7128.23 | N20: 7128.23 | O20: =SUM(C20:E20) -> 67586.15 | P20: =SUM(F20:H20) -> 21384.69 | Q20: =SUM(I20:K20) -> 24417.92 | R20: =SUM(L20:N20) -> 24417.92 | S20: =SUM(C20:N20) -> 137806.68
A21: Podcast | B21: I've Had It | C21: 133545.27 | D21: 158293.19 | E21: 148674.75 | F21: 91927.69 | G21: 70496.34 | H21: 75171.34 | I21: 71673.27 | J21: 60202.34 | O21: =SUM(C21:E21) -> 440513.21 | P21: =SUM(F21:H21) -> 237595.37 | Q21: =SUM(I21:K21) -> 131875.61 | R21: =SUM(L21:N21) -> 0 | S21: =SUM(C21:N21) -> 809984.19
A22: Podcast | B22: Karma and Chaos (Baby Mama) | C22: 41418.5 | D22: 30360.4 | E22: 43684.9 | F22: 19041.6 | G22: 18669.7 | H22: 19275.2 | I22: 21669.7 | J22: 22275.2 | K22: 21669.7 | L22: 24825.2 | M22: 24219.7 | N22: 22325.2 | O22: =SUM(C22:E22) -> 115463.8 | P22: =SUM(F22:H22) -> 56986.5 | Q22: =SUM(I22:K22) -> 65614.6 | R22: =SUM(L22:N22) -> 71370.1 | S22: =SUM(C22:N22) -> 309435
A23: Podcast | B23: LadyGang | C23: 25610 | D23: 48370 | E23: 23740 | F23: 19870 | G23: 14990 | H23: 13870 | I23: 8990 | J23: 7870 | K23: 8990 | L23: 7870 | M23: 8990 | N23: 0 | O23: =SUM(C23:E23) -> 97720 | P23: =SUM(F23:H23) -> 48730 | Q23: =SUM(I23:K23) -> 25850 | R23: =SUM(L23:N23) -> 16860 | S23: =SUM(C23:N23) -> 189160
A24: Podcast | B24: Love Murder | C24: 6771.75 | D24: 6776.75 | E24: 6856.75 | F24: 3266.75 | G24: 2841.75 | H24: 2416.75 | I24: 3266.75 | J24: 2416.75 | K24: 3266.75 | L24: 2841.75 | M24: 2416.75 | N24: 3266.75 | O24: =SUM(C24:E24) -> 20405.25 | P24: =SUM(F24:H24) -> 8525.25 | Q24: =SUM(I24:K24) -> 8950.25 | R24: =SUM(L24:N24) -> 8525.25 | S24: =SUM(C24:N24) -> 46406
A25: Podcast | B25: Mint Arrow Messages | C25: 0 | D25: 0 | O25: =SUM(C25:E25) -> 0 | P25: =SUM(F25:H25) -> 0 | Q25: =SUM(I25:K25) -> 0 | R25: =SUM(L25:N25) -> 0 | S25: =SUM(C25:N25) -> 0
A26: Podcast | B26: Notsam Wrestling | C26: 3045 | D26: 1645 | E26: 2420 | O26: =SUM(C26:E26) -> 7110 | P26: =SUM(F26:H26) -> 0 | Q26: =SUM(I26:K26) -> 0 | R26: =SUM(L26:N26) -> 0 | S26: =SUM(C26:N26) -> 7110
A27: Podcast | B27: Off The Vine with Kaitlyn Bristowe | C27: 81989.84 | D27: 95003.84 | E27: 46827.84 | F27: 22062.84 | G27: 16792.84 | H27: 21630.84 | I27: 9449.84 | J27: 11164.84 | K27: 10694.84 | L27: 9294.84 | M27: 9049.84 | N27: 5779.84 | O27: =SUM(C27:E27) -> 223821.52 | P27: =SUM(F27:H27) -> 60486.52 | Q27: =SUM(I27:K27) -> 31309.52 | R27: =SUM(L27:N27) -> 24124.52 | S27: =SUM(C27:N27) -> 339742.08
A28: Podcast | B28: Our Fake History | C28: 6506.9 | D28: 6481.9 | E28: 10056.9 | F28: 1050 | G28: 1050 | H28: 2100 | I28: 1050 | J28: 1050 | K28: 1050 | L28: 1050 | M28: 1050 | N28: 1050 | O28: =SUM(C28:E28) -> 23045.7 | P28: =SUM(F28:H28) -> 4200 | Q28: =SUM(I28:K28) -> 3150 | R28: =SUM(L28:N28) -> 3150 | S28: =SUM(C28:N28) -> 33545.7
A29: Podcast | B29: Pop Apologists | C29: 36410.8 | D29: 38990.79 | E29: 26615.79 | F29: 19590.79 | G29: 5595.79 | H29: 14590.79 | I29: 13760.79 | J29: 9590.79 | K29: 9590.79 | L29: 9590.79 | M29: 11715.79 | N29: 5595.79 | O29: =SUM(C29:E29) -> 102017.38 | P29: =SUM(F29:H29) -> 39777.37 | Q29: =SUM(I29:K29) -> 32942.37 | R29: =SUM(L29:N29) -> 26902.37 | S29: =SUM(C29:N29) -> 201639.49
A30: Podcast | B30: Some More News | C30: 50116.99 | D30: 46393.74 | E30: 46471.75 | F30: 28696.75 | G30: 23695 | H30: 13695 | I30: 13695 | J30: 13695 | K30: 13695 | L30: 13695 | M30: 13695 | N30: 13695 | O30: =SUM(C30:E30) -> 142982.48 | P30: =SUM(F30:H30) -> 66086.75 | Q30: =SUM(I30:K30) -> 41085 | R30: =SUM(L30:N30) -> 41085 | S30: =SUM(C30:N30) -> 291239.23
A31: Podcast | B31: Stassi | C31: 53442.8 | D31: 47617.81 | E31: 58232.81 | F31: 46340.3 | G31: 27527.8 | H31: 33682.8 | I31: 43407.8 | J31: 33682.8 | K31: 42050.3 | L31: 31817.8 | M31: 40982.8 | N31: 28517.8 | O31: =SUM(C31:E31) -> 159293.42 | P31: =SUM(F31:H31) -> 107550.9 | Q31: =SUM(I31:K31) -> 119140.9 | R31: =SUM(L31:N31) -> 101318.4 | S31: =SUM(C31:N31) -> 487303.62
A32: Podcast | B32: Tactful Pettiness | C32: 2375.6 | D32: 2375.6 | E32: 1775.6 | F32: 1400.6 | G32: 1400.6 | H32: 805.6 | I32: 1995.6 | J32: 1400.6 | K32: 805.6 | L32: 1995.6 | M32: 1400.6 | N32: 1400.6 | O32: =SUM(C32:E32) -> 6526.8 | P32: =SUM(F32:H32) -> 3606.8 | Q32: =SUM(I32:K32) -> 4201.8 | R32: =SUM(L32:N32) -> 4796.8 | S32: =SUM(C32:N32) -> 19132.2
A33: Podcast | B33: The Adam and Dr. Drew Show | C33: 14360.28 | D33: 11722.92 | E33: 41220.28 | F33: 6033.36 | G33: 6790.76 | H33: 5213.32 | I33: 6030.76 | J33: 6733.32 | K33: 6030.76 | L33: 6733.32 | M33: 6030.76 | N33: 5273.36 | O33: =SUM(C33:E33) -> 67303.48 | P33: =SUM(F33:H33) -> 18037.44 | Q33: =SUM(I33:K33) -> 18794.84 | R33: =SUM(L33:N33) -> 18037.44 | S33: =SUM(C33:N33) -> 122173.2
A34: Podcast | B34: The Consult | C34: 400 | D34: 800 | E34: 800 | F34: 800 | G34: 400 | H34: 400 | I34: 400 | J34: 400 | K34: 400 | L34: 400 | M34: 800 | N34: 400 | O34: =SUM(C34:E34) -> 2000 | P34: =SUM(F34:H34) -> 1600 | Q34: =SUM(I34:K34) -> 1200 | R34: =SUM(L34:N34) -> 1600 | S34: =SUM(C34:N34) -> 6400
A35: Podcast | B35: The Dr. Gundry Podcast | C35: 26377.48 | D35: 21072.48 | E35: 24896.47 | F35: 11233.48 | G35: 29533.48 | H35: 9533.48 | I35: 12509.48 | J35: 11533.48 | K35: 10257.48 | L35: 11233.48 | M35: 10981.47 | N35: 14533.48 | O35: =SUM(C35:E35) -> 72346.43 | P35: =SUM(F35:H35) -> 50300.44 | Q35: =SUM(I35:K35) -> 34300.44 | R35: =SUM(L35:N35) -> 36748.43 | S35: =SUM(C35:N35) -> 193695.74
A36: Podcast | B36: The Fighter and the Kid | C36: 37666 | D36: 31311 | E36: 28600 | F36: 4500 | G36: 2250 | H36: 2250 | I36: 2250 | J36: 2250 | K36: 2250 | L36: 2250 | M36: 2250 | N36: 2250 | O36: =SUM(C36:E36) -> 97577 | P36: =SUM(F36:H36) -> 9000 | Q36: =SUM(I36:K36) -> 6750 | R36: =SUM(L36:N36) -> 6750 | S36: =SUM(C36:N36) -> 120077
A37: Podcast | B37: The Golden Hour | C37: 10791 | D37: 15706.99 | E37: 4788 | F37: 2422 | G37: 2422 | H37: 2422 | I37: 2422 | J37: 2422 | K37: 2422 | L37: 2422 | M37: 2422 | N37: 2422 | O37: =SUM(C37:E37) -> 31285.99 | P37: =SUM(F37:H37) -> 7266 | Q37: =SUM(I37:K37) -> 7266 | R37: =SUM(L37:N37) -> 7266 | S37: =SUM(C37:N37) -> 53083.99
A38: Podcast | B38: The James Altucher Show | C38: 233.8 | D38: 1058.76 | E38: 1058.76 | F38: 1058.76 | G38: 233.8 | H38: 233.8 | I38: 233.8 | J38: 233.8 | K38: 233.8 | L38: 233.8 | M38: 233.8 | N38: 233.8 | O38: =SUM(C38:E38) -> 2351.32 | P38: =SUM(F38:H38) -> 1526.36 | Q38: =SUM(I38:K38) -> 701.4 | R38: =SUM(L38:N38) -> 701.4 | S38: =SUM(C38:N38) -> 5280.48
A39: Podcast | B39: The Jordan Harbinger Show | C39: 177262.95 | D39: 135119.27 | E39: 121648.75 | F39: 83284.94 | G39: 71955.98 | H39: 66722.41 | I39: 70809.55 | J39: 63351.7 | K39: 69697.41 | L39: 67463.84 | M39: 68867.69 | N39: 68151.27 | O39: =SUM(C39:E39) -> 434030.97 | P39: =SUM(F39:H39) -> 221963.33 | Q39: =SUM(I39:K39) -> 203858.66 | R39: =SUM(L39:N39) -> 204482.8 | S39: =SUM(C39:N39) -> 1064335.8
A40: Podcast | B40: The Opportunist | C40: 0 | D40: 1360 | E40: 1360 | F40: 1360 | G40: 1360 | H40: 1360 | I40: 1360 | J40: 2720 | L40: 1360 | M40: 1360 | N40: 1360 | O40: =SUM(C40:E40) -> 2720 | P40: =SUM(F40:H40) -> 4080 | Q40: =SUM(I40:K40) -> 4080 | R40: =SUM(L40:N40) -> 4080 | S40: =SUM(C40:N40) -> 14960
A41: Podcast | B41: The Prosecutors | C41: 24063.1 | D41: 20513.1 | E41: 24063.1 | F41: 5248.3 | G41: 5248.3 | H41: 5248.3 | I41: 3548.3 | J41: 3670.79 | K41: 3425.82 | L41: 3548.3 | M41: 3670.79 | N41: 3425.82 | O41: =SUM(C41:E41) -> 68639.3 | P41: =SUM(F41:H41) -> 15744.9 | Q41: =SUM(I41:K41) -> 10644.91 | R41: =SUM(L41:N41) -> 10644.91 | S41: =SUM(C41:N41) -> 105674.02
A42: Podcast | B42: The Schuab Show | C42: 12837 | D42: 7933.5 | E42: 8590 | F42: 2080 | G42: 2080 | H42: 2080 | I42: 2080 | J42: 2080 | K42: 2080 | L42: 2080 | M42: 2080 | N42: 2080 | O42: =SUM(C42:E42) -> 29360.5 | P42: =SUM(F42:H42) -> 6240 | Q42: =SUM(I42:K42) -> 6240 | R42: =SUM(L42:N42) -> 6240 | S42: =SUM(C42:N42) -> 48080.5
A43: Podcast | B43: The Southern Tea | C43: 20414.5 | D43: 23196.5 | E43: 21908.5 | F43: 14540.5 | G43: 11660.5 | H43: 10620.5 | I43: 12460.5 | J43: 12700.5 | K43: 11420.5 | L43: 12700.5 | M43: 12460.5 | N43: 9402.5 | O43: =SUM(C43:E43) -> 65519.5 | P43: =SUM(F43:H43) -> 36821.5 | Q43: =SUM(I43:K43) -> 36581.5 | R43: =SUM(L43:N43) -> 34563.5 | S43: =SUM(C43:N43) -> 173486
A44: Podcast | B44: The Steve Austin Show | C44: 850 | D44: 0 | E44: 0 | O44: =SUM(C44:E44) -> 850 | P44: =SUM(F44:H44) -> 0 | Q44: =SUM(I44:K44) -> 0 | R44: =SUM(L44:N44) -> 0 | S44: =SUM(C44:N44) -> 850
A45: Podcast | B45: Toni Bryanne Podcast | C45: 22172.04 | D45: 27173.43 | E45: 23631.53 | F45: 3400 | O45: =SUM(C45:E45) -> 72977 | P45: =SUM(F45:H45) -> 3400 | Q45: =SUM(I45:K45) -> 0 | R45: =SUM(L45:N45) -> 0 | S45: =SUM(C45:N45) -> 76377
A46: Podcast | B46: True Crime All The Time Unsolved | C46: 10569.1 | D46: 11779.41 | E46: 11059.1 | F46: 1989.1 | G46: 1989.1 | H46: 1989.1 | I46: 1989.1 | J46: 1989.1 | K46: 1989.1 | L46: 1989.1 | M46: 1989.1 | N46: 1989.1 | O46: =SUM(C46:E46) -> 33407.61 | P46: =SUM(F46:H46) -> 5967.3 | Q46: =SUM(I46:K46) -> 5967.3 | R46: =SUM(L46:N46) -> 5967.3 | S46: =SUM(C46:N46) -> 51309.51
A47: Podcast | B47: Unlocked Savannah Chrisley | C47: 33544 | D47: 18787 | E47: 22037 | F47: 5537 | G47: 5537 | H47: 5537 | I47: 5537 | J47: 5537 | K47: 5537 | L47: 5537 | M47: 5537 | N47: 5537 | O47: =SUM(C47:E47) -> 74368 | P47: =SUM(F47:H47) -> 16611 | Q47: =SUM(I47:K47) -> 16611 | R47: =SUM(L47:N47) -> 16611 | S47: =SUM(C47:N47) -> 124201
A48: Podcast | B48: Was I In A Cult | C48: 11868.59 | D48: 9218.59 | E48: 8873.59 | F48: 5198.59 | G48: 5198.59 | H48: 5198.59 | I48: 5198.59 | J48: 5198.59 | K48: 5198.59 | L48: 5198.59 | M48: 5198.59 | N48: 4198.59 | O48: =SUM(C48:E48) -> 29960.77 | P48: =SUM(F48:H48) -> 15595.77 | Q48: =SUM(I48:K48) -> 15595.77 | R48: =SUM(L48:N48) -> 14595.77 | S48: =SUM(C48:N48) -> 75748.08
A49: Podcast | B49: When Reality Hits | C49: 29114 | D49: 22959 | E49: 24339 | F49: 11689 | G49: 14384 | H49: 11689 | I49: 14384 | J49: 11689 | K49: 14384 | L49: 13389 | M49: 16084 | N49: 13389 | O49: =SUM(C49:E49) -> 76412 | P49: =SUM(F49:H49) -> 37762 | Q49: =SUM(I49:K49) -> 40457 | R49: =SUM(L49:N49) -> 42862 | S49: =SUM(C49:N49) -> 197493
A50: Podcast | B50: Your Welcome with Michael Malice | C50: 17970 | D50: 18060 | E50: 13820 | F50: 3370 | G50: 4870 | H50: 6370 | I50: 3370 | J50: 6370 | K50: 4870 | L50: 3370 | M50: 6370 | N50: 3370 | O50: =SUM(C50:E50) -> 49850 | P50: =SUM(F50:H50) -> 14610 | Q50: =SUM(I50:K50) -> 14610 | R50: =SUM(L50:N50) -> 13110 | S50: =SUM(C50:N50) -> 92180
A51: Adswizz | B51: Adam Carolla Show | DAI | C51: 0 | D51: 0 | E51: 0 | O51: =SUM(C51:E51) -> 0 | P51: =SUM(F51:H51) -> 0 | Q51: =SUM(I51:K51) -> 0 | R51: =SUM(L51:N51) -> 0 | S51: =SUM(C51:N51) -> 0
A52: Adswizz | B52: Barely Famous | DAI | C52: 0 | D52: 0 | E52: 1750 | F52: 0 | G52: 0 | H52: 0 | I52: 0 | J52: 0 | K52: 0 | L52: 0 | M52: 0 | N52: 0 | O52: =SUM(C52:E52) -> 1750 | P52: =SUM(F52:H52) -> 0 | Q52: =SUM(I52:K52) -> 0 | R52: =SUM(L52:N52) -> 0 | S52: =SUM(C52:N52) -> 1750
A53: Adswizz | B53: Coffee Convos | DAI | C53: 3689.99 | D53: 3150 | E53: 4229.99 | F53: 3150 | G53: 3150 | H53: 3150 | I53: 3150 | J53: 3150 | K53: 3150 | L53: 3150 | M53: 3150 | N53: 3150 | O53: =SUM(C53:E53) -> 11069.98 | P53: =SUM(F53:H53) -> 9450 | Q53: =SUM(I53:K53) -> 9450 | R53: =SUM(L53:N53) -> 9450 | S53: =SUM(C53:N53) -> 39419.98
A54: Adswizz | B54: I've had it | DAI | C54: 3360 | D54: 0 | E54: 0 | F54: 0 | G54: 0 | H54: 0 | I54: 0 | J54: 0 | O54: =SUM(C54:E54) -> 3360 | P54: =SUM(F54:H54) -> 0 | Q54: =SUM(I54:K54) -> 0 | R54: =SUM(L54:N54) -> 0 | S54: =SUM(C54:N54) -> 3360
A55: Adswizz | B55: Karma and Chaos (Baby Mama) | DAI | C55: 0 | D55: 0 | E55: 181.83 | F55: 2727.28 | G55: 90.9 | H55: 0 | I55: 0 | J55: 0 | K55: 0 | L55: 0 | M55: 0 | N55: 0 | O55: =SUM(C55:E55) -> 181.83 | P55: =SUM(F55:H55) -> 2818.18 | Q55: =SUM(I55:K55) -> 0 | R55: =SUM(L55:N55) -> 0 | S55: =SUM(C55:N55) -> 3000.01
A56: Adswizz | B56: LadyGang | DAI | C56: 2232.38 | D56: 1808.72 | E56: 1148.72 | F56: 1090 | G56: 570 | H56: 1660 | O56: =SUM(C56:E56) -> 5189.82 | P56: =SUM(F56:H56) -> 3320 | Q56: =SUM(I56:K56) -> 0 | R56: =SUM(L56:N56) -> 0 | S56: =SUM(C56:N56) -> 8509.82
A57: Adswizz | B57: Off The Vine with Kaitlyn Bristowe | DAI | C57: 1544 | D57: 1660 | E57: 1300 | F57: 1090 | G57: 570 | H57: 1660 | I57: 0 | J57: 0 | K57: 0 | L57: 0 | M57: 0 | N57: 0 | O57: =SUM(C57:E57) -> 4504 | P57: =SUM(F57:H57) -> 3320 | Q57: =SUM(I57:K57) -> 0 | R57: =SUM(L57:N57) -> 0 | S57: =SUM(C57:N57) -> 7824
A58: Adswizz | B58: PodcastOne | DAI | C58: 146553.25 | D58: 129664.96 | E58: 134558.96 | F58: 19527.95 | G58: 20328.58 | H58: 19527.95 | I58: 20328.58 | J58: 19527.95 | K58: 19527.95 | L58: 20328.58 | M58: 19527.95 | N58: 19527.95 | O58: =SUM(C58:E58) -> 410777.17 | P58: =SUM(F58:H58) -> 59384.48 | Q58: =SUM(I58:K58) -> 59384.48 | R58: =SUM(L58:N58) -> 59384.48 | S58: =SUM(C58:N58) -> 588930.61
A59: Adswizz | B59: Pop Apologists | DAI | C59: 1176 | D59: 2000 | F59: 1326 | G59: 674 | H59: 2000 | O59: =SUM(C59:E59) -> 3176 | P59: =SUM(F59:H59) -> 4000 | Q59: =SUM(I59:K59) -> 0 | R59: =SUM(L59:N59) -> 0 | S59: =SUM(C59:N59) -> 7176
A60: Adswizz | B60: The Fighter and Kid | DAI | C60: 720.12 | D60: 1440.24 | E60: 1440.24 | F60: 1440.24 | G60: 1440.24 | H60: 1440.24 | I60: 1440.24 | J60: 1440.24 | K60: 1440.24 | L60: 1440.24 | M60: 1440.24 | N60: 1440.24 | O60: =SUM(C60:E60) -> 3600.6 | P60: =SUM(F60:H60) -> 4320.72 | Q60: =SUM(I60:K60) -> 4320.72 | R60: =SUM(L60:N60) -> 4320.72 | S60: =SUM(C60:N60) -> 16562.76
A61: Adswizz | B61: The Jordan Harbinger Show | DAI | C61: 17164.59 | D61: 15496.51 | E61: 17939.66 | F61: 10540.4 | G61: 434.36 | O61: =SUM(C61:E61) -> 50600.76 | P61: =SUM(F61:H61) -> 10974.76 | Q61: =SUM(I61:K61) -> 0 | R61: =SUM(L61:N61) -> 0 | S61: =SUM(C61:N61) -> 61575.52
A62: Adswizz | B62: When Reality Hits| DAI | C62: 0 | D62: 0 | E62: 1100 | F62: 0 | G62: 0 | H62: 0 | I62: 0 | J62: 0 | K62: 0 | L62: 0 | M62: 0 | N62: 0 | O62: =SUM(C62:E62) -> 1100 | P62: =SUM(F62:H62) -> 0 | Q62: =SUM(I62:K62) -> 0 | R62: =SUM(L62:N62) -> 0 | S62: =SUM(C62:N62) -> 1100
A63: Social | B63: Adam Carolla Show |Social | C63: 8000 | D63: 0 | E63: 0 | G63: 0 | H63: 0 | J63: 0 | K63: 0 | M63: 0 | N63: 0 | O63: =SUM(C63:E63) -> 8000 | P63: =SUM(F63:H63) -> 0 | Q63: =SUM(I63:K63) -> 0 | R63: =SUM(L63:N63) -> 0 | S63: =SUM(C63:N63) -> 8000
A64: Social | B64: Fool Coverage |Social | D64: 80000 | O64: =SUM(C64:E64) -> 80000 | P64: =SUM(F64:H64) -> 0 | Q64: =SUM(I64:K64) -> 0 | R64: =SUM(L64:N64) -> 0 | S64: =SUM(C64:N64) -> 80000
A65: Social | B65: Off The Vine | Social | D65: 30000 | O65: =SUM(C65:E65) -> 30000 | P65: =SUM(F65:H65) -> 0 | Q65: =SUM(I65:K65) -> 0 | R65: =SUM(L65:N65) -> 0 | S65: =SUM(C65:N65) -> 30000
A66: Social | B66: The Dr. Gundry Podcast | Social | C66: 3000 | I66: 3000 | O66: =SUM(C66:E66) -> 3000 | P66: =SUM(F66:H66) -> 0 | Q66: =SUM(I66:K66) -> 3000 | R66: =SUM(L66:N66) -> 0 | S66: =SUM(C66:N66) -> 6000
A67: Social | B67: The Jordan Harbinger Show | Social | C67: 10625 | O67: =SUM(C67:E67) -> 10625 | P67: =SUM(F67:H67) -> 0 | Q67: =SUM(I67:K67) -> 0 | R67: =SUM(L67:N67) -> 0 | S67: =SUM(C67:N67) -> 10625
A68: Social | B68: The Schaub Show | Social | C68: 14000 | D68: 14000 | O68: =SUM(C68:E68) -> 28000 | P68: =SUM(F68:H68) -> 0 | Q68: =SUM(I68:K68) -> 0 | R68: =SUM(L68:N68) -> 0 | S68: =SUM(C68:N68) -> 28000
A69: Podroll | B69: Adam Carolla Show | C69: 21863.31 | O69: =SUM(C69:E69) -> 21863.31 | P69: =SUM(F69:H69) -> 0 | Q69: =SUM(I69:K69) -> 0 | R69: =SUM(L69:N69) -> 0 | S69: =SUM(C69:N69) -> 21863.31
A70: Podroll | B70: American Justice | C70: 475.57 | O70: =SUM(C70:E70) -> 475.57 | P70: =SUM(F70:H70) -> 0 | Q70: =SUM(I70:K70) -> 0 | R70: =SUM(L70:N70) -> 0 | S70: =SUM(C70:N70) -> 475.57
A71: Podroll | B71: Bad Bad Thing | C71: 33.59 | O71: =SUM(C71:E71) -> 33.59 | P71: =SUM(F71:H71) -> 0 | Q71: =SUM(I71:K71) -> 0 | R71: =SUM(L71:N71) -> 0 | S71: =SUM(C71:N71) -> 33.59
A72: Podroll | B72: City Confidential | C72: 529.71 | O72: =SUM(C72:E72) -> 529.71 | P72: =SUM(F72:H72) -> 0 | Q72: =SUM(I72:K72) -> 0 | R72: =SUM(L72:N72) -> 0 | S72: =SUM(C72:N72) -> 529.71
A73: Podroll | B73: Cold Case Files | C73: 18180.77 | O73: =SUM(C73:E73) -> 18180.77 | P73: =SUM(F73:H73) -> 0 | Q73: =SUM(I73:K73) -> 0 | R73: =SUM(L73:N73) -> 0 | S73: =SUM(C73:N73) -> 18180.77
A74: Podroll | B74: I Survived | C74: 1734.03 | O74: =SUM(C74:E74) -> 1734.03 | P74: =SUM(F74:H74) -> 0 | Q74: =SUM(I74:K74) -> 0 | R74: =SUM(L74:N74) -> 0 | S74: =SUM(C74:N74) -> 1734.03
A75: Podroll | B75: Lost In Panama | C75: 26.05 | O75: =SUM(C75:E75) -> 26.05 | P75: =SUM(F75:H75) -> 0 | Q75: =SUM(I75:K75) -> 0 | R75: =SUM(L75:N75) -> 0 | S75: =SUM(C75:N75) -> 26.05
A76: Podroll | B76: Ransom | C76: 67.66 | O76: =SUM(C76:E76) -> 67.66 | P76: =SUM(F76:H76) -> 0 | Q76: =SUM(I76:K76) -> 0 | R76: =SUM(L76:N76) -> 0 | S76: =SUM(C76:N76) -> 67.66
A77: Podroll | B77: Sex Lies Murder | C77: 19.12 | O77: =SUM(C77:E77) -> 19.12 | P77: =SUM(F77:H77) -> 0 | Q77: =SUM(I77:K77) -> 0 | R77: =SUM(L77:N77) -> 0 | S77: =SUM(C77:N77) -> 19.12
A78: Podroll | B78: The Adam and Dr. Drew Show | C78: 5460.11 | O78: =SUM(C78:E78) -> 5460.11 | P78: =SUM(F78:H78) -> 0 | Q78: =SUM(I78:K78) -> 0 | R78: =SUM(L78:N78) -> 0 | S78: =SUM(C78:N78) -> 5460.11
A79: Podroll | B79: The Fighter and the Kid | C79: 4683.48 | O79: =SUM(C79:E79) -> 4683.48 | P79: =SUM(F79:H79) -> 0 | Q79: =SUM(I79:K79) -> 0 | R79: =SUM(L79:N79) -> 0 | S79: =SUM(C79:N79) -> 4683.48
A80: Podroll | B80: The Golden Hour | C80: 1826.37 | O80: =SUM(C80:E80) -> 1826.37 | P80: =SUM(F80:H80) -> 0 | Q80: =SUM(I80:K80) -> 0 | R80: =SUM(L80:N80) -> 0 | S80: =SUM(C80:N80) -> 1826.37
... A88: PC1 Pro | B88: Love Sac | C88: 13750 | O88: =SUM(C88:E88) -> 13750 | P88: =SUM(F88:H88) -> 0 | Q88: =SUM(I88:K88) -> 0 | R88: =SUM(L88:N88) -> 0 | S88: =SUM(C88:N88) -> 13750
A89: Totals: | B89: Billable Net | C89: =SUM(C2:C88) -> 1762549.9 | D89: =SUM(D2:D88) -> 1633803.6 | E89: =SUM(E2:E88) -> 1452977.4 | F89: =SUM(F2:F88) -> 735496.28 | G89: =SUM(G2:G88) -> 613513.67 | H89: =SUM(H2:H88) -> 604824.98 | I89: =SUM(I2:I88) -> 612871.93 | J89: =SUM(J2:J88) -> 582523.08 | ... S89: =SUM(S2:S88) -> 9782269.8
A90: Totals: | B90: Billable (Gross Advertisers reports as Gross, Net Advertisers As Net) | C90: 1899596.5 | D90: 1726511.1 | E90: 1542353.6 | F90: 787381.36 | G90: 655302.26 | H90: 651255.48 | I90: 659249.67 | J90: 628994.33 | K90: 485598.7 | L90: 489758.84 | M90: 515302 | N90: 418310.83 | O90: =SUM(C90+D90+E90) -> 5168461.2 | P90: =SUM(F90:H90) -> 2093939.1 | Q90: =SUM(I90:K90) -> 1773842.7 | R90: =SUM(L90:N90) -> 1423371.7 | S90: =SUM(C90:N90) -> 10459615
C92: Jan | D92: Feb | E92: March | F92: April | G92: May | H92: June | I92: July | J92: Aug | K92: Sep | L92: Oct | M92: Nov | N92: Dec | O92: Q1 | P92: Q2 | Q92: Q3 | R92: Q4 | S92: Total
B93: DAI Net Total | C93: 176440.34 | D93: 155220.42 | E93: 163649.4 | F93: 40891.86 | G93: 27258.08 | H93: 29438.19 | I93: 24918.82 | J93: 24118.19 | K93: 24118.19 | L93: 24918.82 | M93: 24118.19 | N93: 24118.19 | O93: =SUM(C93:E93) -> 495310.16 | P93: =SUM(F93:H93) -> 97588.13 | Q93: =SUM(I93:K93) -> 73155.2 | R93: =SUM(L93:N93) -> 73155.2 | S93: =SUM(C93:N93) -> 739208.69
B94: DAI Billable Total | C94: 188584.07 | D94: 171806.7 | E94: 180441.42 | F94: 41717.06 | G94: 28083.28 | H94: 30248.23 | I94: 25728.86 | J94: 24928.23 | K94: 24928.23 | L94: 25728.86 | M94: 24928.23 | N94: 24928.23 | O94: =SUM(C94:E94) -> 540832.19 | P94: =SUM(F94:H94) -> 100048.57 | Q94: =SUM(I94:K94) -> 75585.32 | R94: =SUM(L94:N94) -> 75585.32 | S94: =SUM(C94:N94) -> 792051.4
B95: Embedded Net Total | C95: 1478482.5 | D95: 1354583.1 | E95: 1289328 | F95: 694604.41 | G95: 586255.59 | H95: 575386.79 | I95: 584953.12 | J95: 558404.88 | K95: 429061 | L95: 433113.41 | M95: 457125.32 | N95: 367135.8 | O95: =SUM(C95:E95) -> 4122393.7 | P95: =SUM(F95:H95) -> 1856246.8 | Q95: =SUM(I95:K95) -> 1572419 | R95: =SUM(L95:N95) -> 1257374.5 | S95: =SUM(C95:N95) -> 8808434
B96: Embedded Billable Total | C96: 1564550.6 | D96: 1430704.4 | E96: 1361912.1 | F96: 745664.3 | G96: 627218.99 | H96: 621007.25 | I96: 630520.81 | J96: 604066.09 | K96: 460670.47 | L96: 464029.97 | M96: 490373.77 | N96: 393382.6 | O96: =SUM(C96:E96) -> 4357167.2 | P96: =SUM(F96:H96) -> 1993890.5 | Q96: =SUM(I96:K96) -> 1695257.4 | R96: =SUM(L96:N96) -> 1347786.3 | S96: =SUM(C96:N96) -> 9394101.4
B97: Social Net Total | C97: 35625 | D97: 124000 | E97: 0 | F97: 0 | G97: 0 | H97: 0 | I97: 3000 | J97: 0 | K97: 0 | L97: 0 | M97: 0 | N97: 0 | O97: =SUM(C97:E97) -> 159625 | P97: =SUM(F97:H97) -> 0 | Q97: =SUM(I97:K97) -> 3000 | R97: =SUM(L97:N97) -> 0 | S97: =SUM(C97:N97) -> 162625
B98: Social Billable Total | C98: 35625 | D98: 124000 | E98: 0 | F98: 0 | G98: 0 | H98: 0 | I98: 3000 | J98: 0 | K98: 0 | L98: 0 | M98: 0 | N98: 0 | O98: =SUM(C98:E98) -> 159625 | P98: =SUM(F98:H98) -> 0 | Q98: =SUM(I98:K98) -> 3000 | R98: =SUM(L98:N98) -> 0 | S98: =SUM(C98:N98) -> 162625
B99: Pod Roll Net Total | C99: 58252.08 | O99: =SUM(C99:E99) -> 58252.08 | P99: =SUM(F99:H99) -> 0 | Q99: =SUM(I99:K99) -> 0 | R99: =SUM(L99:N99) -> 0 | S99: =SUM(C99:N99) -> 58252.08
B100: Pod Roll Billable Total | C100: 97086.8 | O100: =SUM(C100:E100) -> 97086.8 | P100: =SUM(F100:H100) -> 0 | Q100: =SUM(I100:K100) -> 0 | R100: =SUM(L100:N100) -> 0 | S100: =SUM(C100:N100) -> 97086.8
B101: Podcastone Pro Net Total | C101: 13750 | O101: =SUM(C101:E101) -> 13750 | P101: =SUM(F101:H101) -> 0 | Q101: =SUM(I101:K101) -> 0 | R101: =SUM(L101:N101) -> 0 | S101: =SUM(C101:N101) -> 13750
B102: Podcastone Pro Billable Total | C102: 13750 | O102: =SUM(C102:E102) -> 13750 | P102: =SUM(F102:H102) -> 0 | Q102: =SUM(I102:K102) -> 0 | R102: =SUM(L102:N102) -> 0 | S102: =SUM(C102:N102) -> 13750
B103: PC1 Studio Rental Net Total | O103: =SUM(C103:E103) -> 0 | P103: =SUM(F103:H103) -> 0 | Q103: =SUM(I103:K103) -> 0 | R103: =SUM(L103:N103) -> 0 | S103: =SUM(C103:N103) -> 0
B104: PC1 Studio Rental Billable Total | O104: =SUM(C104:E104) -> 0 | P104: =SUM(F104:H104) -> 0 | Q104: =SUM(I104:K104) -> 0 | R104: =SUM(L104:N104) -> 0 | S104: =SUM(C104:N104) -> 0
C106: =SUM(C93+C95+C97+C99+C101+C103) -> 1762549.9 | D106: =SUM(D93+D95+D97+D99+D101+D103) -> 1633803.6 | E106: =SUM(E93+E95+E97+E99+E101+E103) -> 1452977.4 | F106: =SUM(F93+F95+F97+F99+F101+F103) -> 735496.27 | G106: =SUM(G93+G95+G97+G99+G101+G103) -> 613513.67 | H106: =SUM(H93+H95+H97+H99+H101+H103) -> 604824.98 | I106: =SUM(I93+I95+I97+I99+I101+I103) -> 612871.94 | J106: =SUM(J93+J95+J97+J99+J101+J103) -> 582523.07 | ... N106: =SUM(N93+N95+N97+N99+N101+N103) -> 391253.99
C107: =SUM(C94+C96+C98+C100+C102+C104) -> 1899596.5 | D107: =SUM(D94+D96+D98+D100+D102+D104) -> 1726511.1 | E107: =SUM(E94+E96+E98+E100+E102+E104) -> 1542353.6 | F107: =SUM(F94+F96+F98+F100+F102+F104) -> 787381.36 | G107: =SUM(G94+G96+G98+G100+G102+G104) -> 655302.27 | H107: =SUM(H94+H96+H98+H100+H102+H104) -> 651255.48 | I107: =SUM(I94+I96+I98+I100+I102+I104) -> 659249.67 | J107: =SUM(J94+J96+J98+J100+J102+J104) -> 628994.32 | ... N107: =SUM(N94+N96+N98+N100+N102+N104) -> 418310.83

Sheet Actuals Supports --->

Sheet Dec-2025_IncomeStatement
A1: LiveXLive Media inc | E1: Summary (Breakdown for Actualization)
A2: LiveXLive Media, Inc. : PodcastOne | E2: Pacing Report Category | F2: Revenue Category | G2: Breakdown | H2: Amount
A3: Income Statement | E3: BNB – Embedded Direct | F3: 402004 - Advertising - Podcast | G3: Boostr Billings - Non DAI | H3: 1585324
A4: Dec 2025 | E4: BNB – Embedded Direct | F4: 402004 - Advertising - Podcast | G4: BETOnline Excess Revenue | H4: 15750
E5: BNB – Embedded Direct | F5: 402004 - Advertising - Podcast | G5: AP Bill (Adjustment) | H5: -856.51
E6: BNB – DAI Direct | F6: 402010 - Advertising - DAI | G6: Boostr Billings - DAI | H6: 206218.14
A7: Financial Row | B7: Amount | E7: BNB – Other (social / segments / other) | F7: 402004 - Advertising - Podcast | G7: Boostr Billings - Social | H7: 15000
A8: Ordinary Income/Expense | E8: Programmatic Revenue | F8: 402006 - Advertising - third party | G8: Red Circle December Gross Revenue | H8: 68640.52
A9: Income | E9: Programmatic Revenue | F9: 402006 - Advertising - third party | G9: Triton December Gross Revenue | H9: 35998.66
A10: 400000 - Revenue | E10: Programmatic Revenue | F10: 402006 - Advertising - third party | G10: Adswizz December Gross Revenue | H10: 83774.61
A11: 402000 - Advertising revenue | E11: Programmatic Revenue | F11: 402006 - Advertising - third party | G11: Katz Media December Gross Revenue | H11: 597.15
A12: 402004 - Advertising - Podcast | B12: 1735547.9 | E12: Programmatic Revenue | F12: 402006 - Advertising - third party | G12: Soundstack December Gross Revenue | H12: 5069.46
A13: 402006 - Advertising - third party | B13: 194080.4 | E13: Podroll | F13: 402004 - Advertising - Podcast | G13: Boostr Billings - Non DAI (Podroll_Net Revenue) | H13: 67245.84
A14: 402008 - Advertising - barter | B14: 2246693.9 | E14: Podroll | F14: 402004 - Advertising - Podcast | G14: Boostr Billings - Non DAI (Podroll_Adj to Gross Revenue) | H14: 44834.64
A15: 402010 - Advertising - DAI | B15: 206218.14 | E15: PodcastOne Pro | F15: 402004 - Advertising - Podcast | G15: Boostr Billings - Non DAI (LoveSac) | H15: 8250
A16: 402011 - Advertising - Third Party (TAS) | B16: 520419.54 | E16: Barter | F16: 402008 - Advertising - barter | G16: Barter December Revenues | H16: 2246693.9
A17: Total - 402000 - Advertising revenue | B17: =SUM(B12:B16) -> 4902959.9 | E17: Art 19 - MG or billed | F17: 402011 - Advertising - Third Party (TAS) | G17: ART19 December 2025 Gross Revenue | H17: 354136.4
A18: 409000 - Other revenue | E18: Art 19 - MG or billed | F18: 402011 - Advertising - Third Party (TAS) | G18: ART19 December Payment for Nov-25 Billings | H18: 488372.19 | I18: Net of these two is the excess recognized in Dec-25
A19: 409001 - Other revenue | B19: 135028.99 | E19: Art 19 - MG or billed | F19: 402011 - Advertising - Third Party (TAS) | G19: ART19 November 2025 Gross Revenue already booked prior month | H19: -322089.05 | I19: Net of these two is the excess recognized in Dec-25
A20: Total - 409000 - Other revenue | B20: =SUM(B19) -> 135028.99 | E20: Other Revenues | F20: 409001 - Other revenue | G20: Adam Carolla December 2025 ACS Digital Invoice: | H20: 43896.82
A21: Total - 400000 - Revenue | B21: =SUM(B17,B20) -> 5037988.9 | E21: Other Revenues | F21: 409001 - Other revenue | G21: December 2025 Studio Rental (All Pride, No Ego LLC) | H21: 6125
A22: Total - Income | B22: =SUM(B21) -> 5037988.9 | E22: Other Revenues | F22: 409001 - Other revenue | G22: CBS Studios - Varnamtown Other Revenue | H22: 72843.75
E23: Other Revenues | F23: 409001 - Other revenue | G23: Stripe/Google/Youtube payments (from xx2648) | H23: 4400.42
E24: Other Revenues | F24: 409001 - Other revenue | G24: Stripe/Google/Youtube payments (from xx1499) | H24: 338
E25: Other Revenues | F25: 409001 - Other revenue | G25: Prior Months' Studio Rental (iHeart Media) | H25: 7425
E26: Total Revenue | H26: =SUM(H3:H25) -> 5037988.9

Sheet Adam Carolla_Monthly Breakdown
A1: MOS | B1: YT TOTAL | C1: FACEBOOK | D1: SUBSTACK/STRIPE | E1: RUMBLE | F1: TOTAL MONTHLY SUM
A2: 45992 | B2: 34808.2 | C2: 3570.81 | D2: 5445.96 | E2: 71.85 | F2: =SUM(B2:E2) -> 43896.82
A3: 45962 | B3: 27273.5 | C3: 4244.11 | D3: 10271.39 | E3: 117.9 | F3: =SUM(B3:E3) -> 41906.9
A4: 45931 | B4: 43413.84 | C4: 3583.01 | D4: 5828.27 | E4: 142.35 | F4: =SUM(B4:E4) -> 52967.47
A5: 45901 | B5: 35960.75 | C5: n/a | D5: 22699.3 | E5: 61.06 | F5: =SUM(B5:E5) -> 58721.11
A6: 45870 | B6: 27603.83 | C6: n/a | D6: 13501.01 | E6: 58.94 | F6: =SUM(B6:E6) -> 41163.78
A7: 45839 | B7: 37946.52 | C7: n/a | D7: 4637.72 | E7: 71.33 | F7: =SUM(B7:E7) -> 42655.57
A8: 45809 | B8: 30128.12 | C8: n/a | D8: 9511.14 | E8: 69.7 | F8: =SUM(B8:E8) -> 39708.96
A9: 45778 | B9: 20520.63 | C9: n/a | D9: 4599.23 | E9: 81.66 | F9: =SUM(B9:E9) -> 25201.52
A10: 45748 | B10: 17686.2 | C10: n/a | D10: 4027.42 | E10: 236.93 | F10: =SUM(B10:E10) -> 21950.55
A11: 45717 | B11: 21572.57 | C11: 411.93 | D11: 4059.94 | E11: 192.01 | F11: =SUM(B11:E11) -> 26236.45
A12: 45689 | B12: 22253.14 | C12: 673.94 | D12: 5525.11 | E12: 0 | F12: =SUM(B12:E12) -> 28452.19
A13: 45658 | B13: 28889.13 | C13: 2181.05 | D13: 4403.22 | E13: 0 | F13: =SUM(B13:E13) -> 35473.4
A14: 45627 | B14: 11543.98 | C14: 538.81 | D14: 4381.09 | E14: 0 | F14: =SUM(B14:E14) -> 16463.88
A15: 45597 | B15: 14125.72 | D15: 0 | E15: 0 | F15: =SUM(B15:E15) -> 14125.72
A16: 45566 | B16: 14394.43 | D16: 7342.43 | E16: 0 | F16: =SUM(B16:E16) -> 21736.86
A17: 45536 | B17: 11080.7 | D17: 19408.45 | E17: 0 | F17: =SUM(B17:E17) -> 30489.15
A18: 45505 | B18: 10611.96 | D18: -44.84 | E18: 0 | F18: =SUM(B18:E18) -> 10567.12
A19: 45474 | B19: 11089.3 | D19: 0 | E19: 0 | F19: =SUM(B19:E19) -> 11089.3
A20: 45444 | B20: 11807.41 | D20: 0 | E20: 0 | F20: =SUM(B20:E20) -> 11807.41
A21: 45413 | B21: 11108.54 | D21: 0 | E21: 0 | F21: =SUM(B21:E21) -> 11108.54
A22: 45383 | B22: 9016.27 | D22: 0 | E22: 0 | F22: =SUM(B22:E22) -> 9016.27
A23: 45352 | B23: 8834.23 | D23: 0 | E23: 0 | F23: =SUM(B23:E23) -> 8834.23
A24: 45323 | B24: 9585.41 | D24: 0 | E24: 0 | F24: =SUM(B24:E24) -> 9585.41
A25: 45292 | B25: 7584.57 | D25: 0 | E25: 0 | F25: =SUM(B25:E25) -> 7584.57

Sheet ART19 Summary_YTD
B1: Apr | D1: May | F1: June | H1: July | J1: August | L1: September | N1: October | P1: November | R1: December | T1: Total Revenue Recognized as of 12/31/2025
B2: dr | C2: cr | D2: dr | E2: cr | F2: dr | G2: cr | H2: dr | I2: cr | J2: dr | K2: cr | L2: dr | M2: cr | N2: dr | O2: cr | P2: dr | Q2: cr | R2: dr | S2: cr
A3: Net Revenue | B3: 305563.2 | D3: 322001.42 | F3: 331176.84 | H3: 313214.42 | J3: 392605.79 | L3: 393206.96 | N3: 297098.55 | P3: 322089.05 | R3: 212481.84
A4: Agency Fee | B4: 203708.81 | D4: 214667.61 | F4: 220784.56 | H4: 208809.61 | J4: 261737.19 | L4: 262137.97 | N4: 198065.7 | P4: 214726.03 | R4: 141654.56
A5: Gross Revenue | C5: 509272.01 | E5: 536669.03 | G5: 551961.39 | I5: 522024.03 | K5: 654342.99 | M5: =SUM(L3:L4) -> 655344.93 | O5: =SUM(N3:N4) -> 495164.25 | Q5: =SUM(P3:P4) -> 536815.08 | S5: =SUM(R3:R4) -> 354136.4 | T5: =SUM(B5:S5) -> 4815730.1
A7: MG Payment | B7: 450000 | D7: 450000 | F7: 447667.36 | H7: 447620.27 | J7: 490823.31 | L7: 490218.63 | N7: 487820.49 | P7: 488372.19 | R7: 0
A8: Net Revenue | C8: 305563.2 | E8: 322001.42 | G8: 331176.84 | I8: 313214.42 | K8: 392605.79 | M8: =L3 -> 393206.96 | O8: =N3 -> 297098.55 | Q8: =P3 -> 322089.05 | S8: 212481.84
A9: Adjustment (Excess MG Payment) | C9: =B7-C8 -> 144436.8 | E9: =D7-E8 -> 127998.58 | G9: =F7-G8 -> 116490.52 | I9: =H7-I8 -> 134405.85 | K9: =J7-K8 -> 98217.518 | M9: =L7-M8 -> 97011.672 | O9: =N7-O8 -> 190721.94 | Q9: =P7-Q8 -> 166283.14 | S9: 0 | T9: =SUM(B9:S9) -> 1075566
T10: =SUM(T3:T9) -> 5891296.1

Sheet Ellie Summary
B4: Ellie Programmatic
C5: Jan | D5: Feb | E5: Mar | F5: Total
B6: Forecast
B7: Programmatic Revenue | C7: 80000 | D7: 100000 | E7: 120000 | F7: =SUM(C7:E7) -> 300000
B8: Art 19 - MG or billed | C8: 275000 | D8: 365000 | E8: 410000 | F8: =SUM(C8:E8) -> 1050000
B9: Total | C9: =SUM(C7:C8) -> 355000 | D9: =SUM(D7:D8) -> 465000 | E9: =SUM(E7:E8) -> 530000 | F9: =SUM(C9:E9) -> 1350000
B11: Actual
B12: Programmatic Revenue | C12: 302152.21 | D12: =D7 -> 100000 | E12: =E7 -> 120000 | F12: =SUM(C12:E12) -> 522152.21
B13: Art 19 - MG or billed | C13: 0 | D13: =D8 -> 365000 | E13: =E8 -> 410000 | F13: =SUM(C13:E13) -> 775000
B14: Total | C14: =SUM(C12:C13) -> 302152.21 | D14: =SUM(D12:D13) -> 465000 | E14: =SUM(E12:E13) -> 530000 | F14: =SUM(C14:E14) -> 1297152.2
B16: Variance | C16: =C14-C9 -> -52847.79 | D16: =D14-D9 -> 0 | E16: =E14-E9 -> 0 | F16: =F14-F9 -> -52847.79
B17: + over budget / - under budget
